{
  "CONTRADA BAIANO": [
    {
      "civico": "23",
      "barrato": "A"
    },
    {
      "civico": "83",
      "barrato": "A"
    },
    {
      "civico": "147",
      "barrato": null
    }
  ],
  "CONTRADA BRAIOLE": [
    {
      "civico": "18",
      "barrato": "A"
    },
    {
      "civico": "22",
      "barrato": "A"
    }
  ],
  "CONTRADA BRAUDIANO": [
    {
      "civico": "7",
      "barrato": "8"
    },
    {
      "civico": "9",
      "barrato": "10"
    },
    {
      "civico": "18",
      "barrato": "N"
    },
    {
      "civico": "23",
      "barrato": "PT"
    },
    {
      "civico": "26",
      "barrato": "A"
    },
    {
      "civico": "37",
      "barrato": "A"
    },
    {
      "civico": "54",
      "barrato": "A"
    }
  ],
  "CONTRADA COSTE FONTANA": [
    {
      "civico": "3",
      "barrato": "4"
    }
  ],
  "CONTRADA SAN MARCIANO": [
    {
      "civico": "1",
      "barrato": "2"
    },
    {
      "civico": "7",
      "barrato": "8"
    }
  ],
  "CONTRADA SANT'EUSTACCHIO": [
    {
      "civico": "8",
      "barrato": "9"
    }
  ],
  "CONTRADA TOPPOLO DEL SANTISSIMO": [
    {
      "civico": "1",
      "barrato": "A"
    }
  ],
  "CONTRADA VALLE": [
    {
      "civico": "1",
      "barrato": "S"
    },
    {
      "civico": "3",
      "barrato": "S"
    },
    {
      "civico": "13",
      "barrato": "S"
    },
    {
      "civico": "15",
      "barrato": "S"
    },
    {
      "civico": "17",
      "barrato": "S"
    }
  ],
  "CONTRADA VALLICELLI": [
    {
      "civico": "0",
      "barrato": "SNC"
    },
    {
      "civico": "0",
      "barrato": null
    },
    {
      "civico": "3",
      "barrato": "4"
    },
    {
      "civico": "10",
      "barrato": "11"
    },
    {
      "civico": "10",
      "barrato": "A"
    },
    {
      "civico": "18",
      "barrato": null
    },
    {
      "civico": "48",
      "barrato": "A"
    },
    {
      "civico": "49",
      "barrato": "A"
    },
    {
      "civico": "55",
      "barrato": "A"
    }
  ],
  "PIAZZA LARGO SOCCORSO": [
    {
      "civico": "2",
      "barrato": "4"
    }
  ],
  "PIAZZA MUNICIPIO": [
    {
      "civico": "9",
      "barrato": "11"
    },
    {
      "civico": "10",
      "barrato": "12"
    }
  ],
  "VIA BRANCIA": [
    {
      "civico": "2",
      "barrato": "4"
    }
  ],
  "VIA CALABRESE": [
    {
      "civico": "1",
      "barrato": "A"
    },
    {
      "civico": "3",
      "barrato": "5"
    }
  ],
  "VIA CAPO GIARDINO": [
    {
      "civico": "4",
      "barrato": "F"
    },
    {
      "civico": "4",
      "barrato": "S"
    },
    {
      "civico": "5",
      "barrato": "7"
    },
    {
      "civico": "8",
      "barrato": "F"
    },
    {
      "civico": "8",
      "barrato": "S"
    },
    {
      "civico": "10",
      "barrato": "F"
    },
    {
      "civico": "10",
      "barrato": "S"
    },
    {
      "civico": "25",
      "barrato": "F"
    },
    {
      "civico": "25",
      "barrato": "S"
    },
    {
      "civico": "28",
      "barrato": "F"
    },
    {
      "civico": "28",
      "barrato": "S"
    }
  ],
  "VIA CIRCONDARIO": [
    {
      "civico": "4",
      "barrato": "A"
    }
  ],
  "VIA CONCEZIONE": [
    {
      "civico": "2",
      "barrato": "A"
    }
  ],
  "VIA FONTANA MARENA": [
    {
      "civico": "4",
      "barrato": null
    },
    {
      "civico": "6",
      "barrato": null
    },
    {
      "civico": "8",
      "barrato": null
    },
    {
      "civico": "10",
      "barrato": null
    }
  ],
  "VIA FORIA": [
    {
      "civico": "14",
      "barrato": "C"
    },
    {
      "civico": "14",
      "barrato": "S"
    }
  ],
  "VIA RIVIERA SUL CALORE": [
    {
      "civico": "1",
      "barrato": "A"
    },
    {
      "civico": "9",
      "barrato": "11"
    }
  ],
  "VIA ROMA": [
    {
      "civico": "1",
      "barrato": "A"
    },
    {
      "civico": "4",
      "barrato": "A"
    },
    {
      "civico": "8",
      "barrato": "10"
    },
    {
      "civico": "24",
      "barrato": null
    }
  ],
  "VIA RUPE TARPEIA": [
    {
      "civico": "9",
      "barrato": "11"
    }
  ],
  "VIA SANT'EUSTACCHIO": [
    {
      "civico": "1",
      "barrato": "Z"
    },
    {
      "civico": "2",
      "barrato": "Z"
    },
    {
      "civico": "3",
      "barrato": "Z"
    },
    {
      "civico": "4",
      "barrato": "Z"
    },
    {
      "civico": "5",
      "barrato": "Z"
    },
    {
      "civico": "6",
      "barrato": "Z"
    },
    {
      "civico": "7",
      "barrato": "E"
    },
    {
      "civico": "7",
      "barrato": "P"
    },
    {
      "civico": "8",
      "barrato": "P"
    },
    {
      "civico": "8",
      "barrato": "Z"
    },
    {
      "civico": "9",
      "barrato": "10"
    },
    {
      "civico": "9",
      "barrato": "P"
    },
    {
      "civico": "10",
      "barrato": "Z"
    },
    {
      "civico": "12",
      "barrato": "Z"
    },
    {
      "civico": "13",
      "barrato": "Z"
    },
    {
      "civico": "14",
      "barrato": "Z"
    },
    {
      "civico": "16",
      "barrato": "Z"
    },
    {
      "civico": "18",
      "barrato": "Z"
    },
    {
      "civico": "19",
      "barrato": "Z"
    },
    {
      "civico": "20",
      "barrato": "Z"
    },
    {
      "civico": "21",
      "barrato": "Z"
    },
    {
      "civico": "22",
      "barrato": "Z"
    },
    {
      "civico": "23",
      "barrato": "Z"
    },
    {
      "civico": "24",
      "barrato": "Z"
    },
    {
      "civico": "25",
      "barrato": "Z"
    },
    {
      "civico": "26",
      "barrato": "Z"
    },
    {
      "civico": "28",
      "barrato": "Z"
    },
    {
      "civico": "32",
      "barrato": "Z"
    },
    {
      "civico": "33",
      "barrato": "A"
    },
    {
      "civico": "33",
      "barrato": "Z"
    },
    {
      "civico": "34",
      "barrato": "Z"
    },
    {
      "civico": "35",
      "barrato": "Z"
    },
    {
      "civico": "40",
      "barrato": "Z"
    },
    {
      "civico": "41",
      "barrato": "A"
    },
    {
      "civico": "41",
      "barrato": "B"
    },
    {
      "civico": "42",
      "barrato": "Z"
    },
    {
      "civico": "43",
      "barrato": "Z"
    },
    {
      "civico": "44",
      "barrato": "Z"
    },
    {
      "civico": "45",
      "barrato": "Z"
    },
    {
      "civico": "46",
      "barrato": "Z"
    },
    {
      "civico": "48",
      "barrato": "A"
    },
    {
      "civico": "48",
      "barrato": "Z"
    },
    {
      "civico": "52",
      "barrato": "A"
    }
  ],
  "VIA SOTTOCORTE": [
    {
      "civico": "2",
      "barrato": "4"
    },
    {
      "civico": "5",
      "barrato": "7"
    },
    {
      "civico": "8",
      "barrato": "10"
    },
    {
      "civico": "9",
      "barrato": "11"
    }
  ],
  "VIA STELLA": [
    {
      "civico": "3",
      "barrato": "5"
    }
  ],
  "VIA VADANTICO": [
    {
      "civico": "1",
      "barrato": "A"
    },
    {
      "civico": "1",
      "barrato": "N"
    },
    {
      "civico": "1",
      "barrato": "Z"
    },
    {
      "civico": "5",
      "barrato": "N"
    },
    {
      "civico": "6",
      "barrato": "Z"
    },
    {
      "civico": "9",
      "barrato": "Z"
    },
    {
      "civico": "10",
      "barrato": "D"
    },
    {
      "civico": "10",
      "barrato": "Z"
    },
    {
      "civico": "13",
      "barrato": "Z"
    },
    {
      "civico": "14",
      "barrato": "Z"
    },
    {
      "civico": "18",
      "barrato": "Z"
    },
    {
      "civico": "20",
      "barrato": "Z"
    },
    {
      "civico": "22",
      "barrato": "Z"
    },
    {
      "civico": "24",
      "barrato": "Z"
    },
    {
      "civico": "26",
      "barrato": "Z"
    }
  ],
  "VIA VENEZIA": [
    {
      "civico": "1",
      "barrato": "Z"
    },
    {
      "civico": "3",
      "barrato": "Z"
    },
    {
      "civico": "4",
      "barrato": "6"
    },
    {
      "civico": "4",
      "barrato": "Z"
    },
    {
      "civico": "5",
      "barrato": "Z"
    },
    {
      "civico": "6",
      "barrato": "Z"
    },
    {
      "civico": "7",
      "barrato": "Z"
    },
    {
      "civico": "8",
      "barrato": "Z"
    },
    {
      "civico": "9",
      "barrato": "11"
    },
    {
      "civico": "9",
      "barrato": "Z"
    },
    {
      "civico": "10",
      "barrato": "Z"
    },
    {
      "civico": "11",
      "barrato": "Z"
    },
    {
      "civico": "12",
      "barrato": "Z"
    },
    {
      "civico": "16",
      "barrato": "Z"
    }
  ]
}