{
  "CASCINA BERLOCCA": [
    {
      "civico": "0",
      "barrato": "SNC"
    },
    {
      "civico": "0",
      "barrato": null
    }
  ],
  "PASSAGGIO BELVISO": [
    {
      "civico": "111",
      "barrato": null
    }
  ],
  "PIAZZA DEL COMUNE": [
    {
      "civico": "1",
      "barrato": null
    },
    {
      "civico": "3",
      "barrato": null
    },
    {
      "civico": "5",
      "barrato": null
    },
    {
      "civico": "7",
      "barrato": null
    },
    {
      "civico": "9",
      "barrato": null
    },
    {
      "civico": "11",
      "barrato": null
    }
  ],
  "VIA ALBERTO DA GIUSSANO": [
    {
      "civico": "1",
      "barrato": null
    },
    {
      "civico": "79",
      "barrato": null
    },
    {
      "civico": "85",
      "barrato": null
    },
    {
      "civico": "87",
      "barrato": null
    },
    {
      "civico": "89",
      "barrato": null
    },
    {
      "civico": "115",
      "barrato": null
    },
    {
      "civico": "121",
      "barrato": null
    },
    {
      "civico": "123",
      "barrato": null
    },
    {
      "civico": "125",
      "barrato": null
    }
  ],
  "VIA CASTELLANA": [
    {
      "civico": "3",
      "barrato": null
    },
    {
      "civico": "15",
      "barrato": "A"
    }
  ],
  "VIA DEL CARROCCIO": [
    {
      "civico": "170",
      "barrato": null
    },
    {
      "civico": "180",
      "barrato": null
    },
    {
      "civico": "183",
      "barrato": null
    }
  ],
  "VIA FIUME PO": [
    {
      "civico": "277",
      "barrato": null
    },
    {
      "civico": "315",
      "barrato": null
    }
  ],
  "VIA PONTIDA": [
    {
      "civico": "0",
      "barrato": null
    },
    {
      "civico": "1",
      "barrato": null
    }
  ]
}