{
  "BORGATA BAUDINI": [
    {
      "civico": "3",
      "barrato": null
    }
  ],
  "BORGATA CHIOSSO": [
    {
      "civico": "5",
      "barrato": null
    }
  ],
  "BORGATA CLARI": [
    {
      "civico": "1",
      "barrato": null
    }
  ],
  "BORGATA GORIA DI MEZZO": [
    {
      "civico": "1",
      "barrato": null
    },
    {
      "civico": "2",
      "barrato": null
    },
    {
      "civico": "3",
      "barrato": null
    },
    {
      "civico": "4",
      "barrato": null
    },
    {
      "civico": "5",
      "barrato": null
    }
  ],
  "BORGATA GORIA SUPERIORE": [
    {
      "civico": "1",
      "barrato": null
    },
    {
      "civico": "2",
      "barrato": null
    },
    {
      "civico": "3",
      "barrato": null
    }
  ],
  "BORGATA GRANGE LAURENTI": [
    {
      "civico": "11",
      "barrato": null
    }
  ],
  "BORGATA GRANGE VIANI": [
    {
      "civico": "11",
      "barrato": null
    }
  ],
  "BORGATA GRANGETTE": [
    {
      "civico": "2",
      "barrato": null
    },
    {
      "civico": "3",
      "barrato": null
    }
  ],
  "BORGATA LISCHIA": [
    {
      "civico": "1",
      "barrato": null
    },
    {
      "civico": "4",
      "barrato": null
    }
  ],
  "BORGATA MARTINI": [
    {
      "civico": "3",
      "barrato": null
    },
    {
      "civico": "5",
      "barrato": null
    },
    {
      "civico": "6",
      "barrato": null
    },
    {
      "civico": "8",
      "barrato": null
    },
    {
      "civico": "10",
      "barrato": null
    },
    {
      "civico": "11",
      "barrato": null
    },
    {
      "civico": "12",
      "barrato": null
    },
    {
      "civico": "14",
      "barrato": null
    },
    {
      "civico": "23",
      "barrato": null
    },
    {
      "civico": "24",
      "barrato": null
    }
  ],
  "BORGATA MATTALIA": [
    {
      "civico": "0",
      "barrato": "SNC"
    },
    {
      "civico": "45",
      "barrato": null
    }
  ],
  "BORGATA RINAUD": [
    {
      "civico": "4",
      "barrato": null
    },
    {
      "civico": "5",
      "barrato": null
    },
    {
      "civico": "6",
      "barrato": null
    }
  ],
  "BORGATA SERRE": [
    {
      "civico": "18",
      "barrato": null
    },
    {
      "civico": "20",
      "barrato": null
    },
    {
      "civico": "21",
      "barrato": null
    },
    {
      "civico": "22",
      "barrato": null
    },
    {
      "civico": "23",
      "barrato": null
    },
    {
      "civico": "24",
      "barrato": null
    },
    {
      "civico": "25",
      "barrato": null
    },
    {
      "civico": "26",
      "barrato": null
    },
    {
      "civico": "28",
      "barrato": null
    }
  ],
  "BORGATA VILLAR": [
    {
      "civico": "1",
      "barrato": "B"
    },
    {
      "civico": "2",
      "barrato": null
    },
    {
      "civico": "3",
      "barrato": null
    },
    {
      "civico": "4",
      "barrato": "A"
    },
    {
      "civico": "5",
      "barrato": null
    },
    {
      "civico": "6",
      "barrato": null
    },
    {
      "civico": "7",
      "barrato": null
    },
    {
      "civico": "8",
      "barrato": null
    }
  ],
  "BORGO UGO GORIA": [
    {
      "civico": "1",
      "barrato": null
    },
    {
      "civico": "2",
      "barrato": null
    },
    {
      "civico": "3",
      "barrato": null
    },
    {
      "civico": "9",
      "barrato": null
    }
  ]
}