{
  "VIA BORRO TRE FOSSATI": [
    {
      "civico": "0",
      "barrato": null
    }
  ],
  "VIA BRANCOLANO": [
    {
      "civico": "0",
      "barrato": null
    }
  ],
  "VIA CASA COMUNALE": [
    {
      "civico": "1",
      "barrato": null
    },
    {
      "civico": "9",
      "barrato": null
    },
    {
      "civico": "35",
      "barrato": null
    }
  ],
  "VIA CASSIA": [
    {
      "civico": "173",
      "barrato": null
    },
    {
      "civico": "177",
      "barrato": null
    },
    {
      "civico": "179",
      "barrato": null
    },
    {
      "civico": "181",
      "barrato": null
    },
    {
      "civico": "183",
      "barrato": null
    },
    {
      "civico": "185",
      "barrato": null
    },
    {
      "civico": "187",
      "barrato": null
    },
    {
      "civico": "189",
      "barrato": null
    },
    {
      "civico": "193",
      "barrato": "A"
    },
    {
      "civico": "193",
      "barrato": null
    },
    {
      "civico": "195",
      "barrato": null
    },
    {
      "civico": "197",
      "barrato": null
    },
    {
      "civico": "199",
      "barrato": null
    },
    {
      "civico": "201",
      "barrato": null
    },
    {
      "civico": "213",
      "barrato": null
    },
    {
      "civico": "215",
      "barrato": null
    },
    {
      "civico": "243",
      "barrato": null
    },
    {
      "civico": "245",
      "barrato": "B"
    },
    {
      "civico": "288",
      "barrato": "A"
    },
    {
      "civico": "288",
      "barrato": null
    },
    {
      "civico": "290",
      "barrato": null
    },
    {
      "civico": "292",
      "barrato": null
    },
    {
      "civico": "294",
      "barrato": null
    },
    {
      "civico": "296",
      "barrato": null
    },
    {
      "civico": "298",
      "barrato": null
    },
    {
      "civico": "300",
      "barrato": null
    },
    {
      "civico": "302",
      "barrato": null
    },
    {
      "civico": "304",
      "barrato": null
    },
    {
      "civico": "306",
      "barrato": null
    },
    {
      "civico": "308",
      "barrato": null
    },
    {
      "civico": "310",
      "barrato": null
    },
    {
      "civico": "312",
      "barrato": null
    },
    {
      "civico": "314",
      "barrato": null
    },
    {
      "civico": "316",
      "barrato": null
    }
  ],
  "VIA CHIANTIGIANA PER IL FERRONE": [
    {
      "civico": "0",
      "barrato": "SNC"
    },
    {
      "civico": "51",
      "barrato": "B"
    }
  ],
  "VIA CHIANTIGIANA PER STRADA": [
    {
      "civico": "0",
      "barrato": null
    },
    {
      "civico": "1",
      "barrato": null
    },
    {
      "civico": "3",
      "barrato": null
    },
    {
      "civico": "15",
      "barrato": null
    },
    {
      "civico": "17",
      "barrato": null
    },
    {
      "civico": "19",
      "barrato": "A"
    },
    {
      "civico": "19",
      "barrato": "B"
    },
    {
      "civico": "19",
      "barrato": null
    },
    {
      "civico": "21",
      "barrato": null
    },
    {
      "civico": "23",
      "barrato": null
    },
    {
      "civico": "25",
      "barrato": null
    },
    {
      "civico": "33",
      "barrato": "1"
    },
    {
      "civico": "33",
      "barrato": "10"
    },
    {
      "civico": "33",
      "barrato": "11"
    },
    {
      "civico": "33",
      "barrato": "12"
    },
    {
      "civico": "33",
      "barrato": "13"
    },
    {
      "civico": "33",
      "barrato": "14"
    },
    {
      "civico": "33",
      "barrato": "15"
    },
    {
      "civico": "33",
      "barrato": "2"
    },
    {
      "civico": "33",
      "barrato": "3"
    },
    {
      "civico": "33",
      "barrato": "4"
    },
    {
      "civico": "33",
      "barrato": "5"
    },
    {
      "civico": "33",
      "barrato": "6"
    },
    {
      "civico": "33",
      "barrato": "7"
    },
    {
      "civico": "33",
      "barrato": "8"
    },
    {
      "civico": "33",
      "barrato": "9"
    },
    {
      "civico": "33",
      "barrato": null
    }
  ],
  "VIA COLLERAMOLE": [
    {
      "civico": "4",
      "barrato": "B"
    },
    {
      "civico": "4",
      "barrato": "C"
    },
    {
      "civico": "4",
      "barrato": null
    },
    {
      "civico": "6",
      "barrato": null
    },
    {
      "civico": "8",
      "barrato": null
    },
    {
      "civico": "10",
      "barrato": "A"
    },
    {
      "civico": "10",
      "barrato": null
    },
    {
      "civico": "12",
      "barrato": null
    }
  ],
  "VIA DEI BARUFFI": [
    {
      "civico": "15",
      "barrato": null
    },
    {
      "civico": "17",
      "barrato": null
    },
    {
      "civico": "36",
      "barrato": "A"
    },
    {
      "civico": "36",
      "barrato": "B"
    },
    {
      "civico": "36",
      "barrato": "C"
    }
  ],
  "VIA DEL FERRONE": [
    {
      "civico": "76",
      "barrato": "A"
    },
    {
      "civico": "76",
      "barrato": null
    },
    {
      "civico": "78",
      "barrato": null
    },
    {
      "civico": "82",
      "barrato": null
    }
  ],
  "VIA DELLA BIFONICA": [
    {
      "civico": "30",
      "barrato": null
    },
    {
      "civico": "32",
      "barrato": null
    },
    {
      "civico": "58",
      "barrato": null
    },
    {
      "civico": "62",
      "barrato": null
    },
    {
      "civico": "64",
      "barrato": null
    }
  ],
  "VIA DELLE SODERA": [
    {
      "civico": "16",
      "barrato": null
    },
    {
      "civico": "51",
      "barrato": "B"
    },
    {
      "civico": "51",
      "barrato": null
    },
    {
      "civico": "53",
      "barrato": "D"
    },
    {
      "civico": "53",
      "barrato": null
    },
    {
      "civico": "55",
      "barrato": null
    },
    {
      "civico": "57",
      "barrato": null
    }
  ],
  "VIA DELLE TERRE BIANCHE": [
    {
      "civico": "0",
      "barrato": "SNC 13"
    }
  ],
  "VIA DI CAMPIANO": [
    {
      "civico": "0",
      "barrato": null
    },
    {
      "civico": "3",
      "barrato": "D"
    },
    {
      "civico": "7",
      "barrato": null
    },
    {
      "civico": "11",
      "barrato": null
    }
  ],
  "VIA DI CAPPELLO": [
    {
      "civico": "14",
      "barrato": "A"
    },
    {
      "civico": "14",
      "barrato": null
    },
    {
      "civico": "16",
      "barrato": "A"
    },
    {
      "civico": "18",
      "barrato": null
    },
    {
      "civico": "38",
      "barrato": null
    },
    {
      "civico": "40",
      "barrato": null
    },
    {
      "civico": "48",
      "barrato": null
    }
  ],
  "VIA DI CASTELLO": [
    {
      "civico": "9",
      "barrato": null
    }
  ],
  "VIA DI COLLINE": [
    {
      "civico": "2",
      "barrato": "1"
    }
  ],
  "VIA DI VALIANO": [
    {
      "civico": "1",
      "barrato": null
    },
    {
      "civico": "3",
      "barrato": "A"
    },
    {
      "civico": "3",
      "barrato": null
    },
    {
      "civico": "5",
      "barrato": "A"
    },
    {
      "civico": "5",
      "barrato": "B"
    },
    {
      "civico": "5",
      "barrato": "C"
    },
    {
      "civico": "5",
      "barrato": "F"
    },
    {
      "civico": "5",
      "barrato": null
    },
    {
      "civico": "7",
      "barrato": "A"
    },
    {
      "civico": "7",
      "barrato": null
    },
    {
      "civico": "9",
      "barrato": "A"
    },
    {
      "civico": "9",
      "barrato": null
    },
    {
      "civico": "11",
      "barrato": null
    },
    {
      "civico": "15",
      "barrato": null
    }
  ],
  "VIA FABBIOLLE": [
    {
      "civico": "13",
      "barrato": null
    },
    {
      "civico": "15",
      "barrato": "A"
    },
    {
      "civico": "15",
      "barrato": "B"
    },
    {
      "civico": "15",
      "barrato": null
    },
    {
      "civico": "17",
      "barrato": "A"
    },
    {
      "civico": "17",
      "barrato": "B"
    },
    {
      "civico": "17",
      "barrato": "C"
    },
    {
      "civico": "17",
      "barrato": "D"
    },
    {
      "civico": "17",
      "barrato": "E"
    },
    {
      "civico": "17",
      "barrato": null
    },
    {
      "civico": "18",
      "barrato": "A"
    },
    {
      "civico": "18",
      "barrato": "B"
    },
    {
      "civico": "18",
      "barrato": "C"
    },
    {
      "civico": "18",
      "barrato": "D"
    },
    {
      "civico": "18",
      "barrato": null
    },
    {
      "civico": "19",
      "barrato": null
    },
    {
      "civico": "20",
      "barrato": null
    },
    {
      "civico": "22",
      "barrato": null
    },
    {
      "civico": "24",
      "barrato": "A"
    },
    {
      "civico": "24",
      "barrato": "B"
    },
    {
      "civico": "24",
      "barrato": "BIS"
    },
    {
      "civico": "24",
      "barrato": null
    },
    {
      "civico": "26",
      "barrato": null
    },
    {
      "civico": "28",
      "barrato": "A"
    },
    {
      "civico": "36",
      "barrato": null
    },
    {
      "civico": "38",
      "barrato": "A"
    },
    {
      "civico": "38",
      "barrato": null
    },
    {
      "civico": "40",
      "barrato": null
    },
    {
      "civico": "42",
      "barrato": null
    },
    {
      "civico": "46",
      "barrato": null
    },
    {
      "civico": "48",
      "barrato": null
    },
    {
      "civico": "50",
      "barrato": null
    },
    {
      "civico": "52",
      "barrato": null
    },
    {
      "civico": "54",
      "barrato": null
    },
    {
      "civico": "56",
      "barrato": null
    },
    {
      "civico": "58",
      "barrato": "A"
    },
    {
      "civico": "58",
      "barrato": null
    },
    {
      "civico": "60",
      "barrato": null
    },
    {
      "civico": "76",
      "barrato": "A"
    }
  ],
  "VIA FALCIANI": [
    {
      "civico": "12",
      "barrato": null
    },
    {
      "civico": "54",
      "barrato": null
    },
    {
      "civico": "56",
      "barrato": "A"
    },
    {
      "civico": "56",
      "barrato": null
    },
    {
      "civico": "60",
      "barrato": null
    }
  ],
  "VIA FONTE SECONDA": [
    {
      "civico": "6",
      "barrato": null
    },
    {
      "civico": "26",
      "barrato": "A"
    },
    {
      "civico": "34",
      "barrato": "A"
    },
    {
      "civico": "34",
      "barrato": "B"
    },
    {
      "civico": "34",
      "barrato": "D"
    },
    {
      "civico": "34",
      "barrato": "E"
    },
    {
      "civico": "34",
      "barrato": "F"
    },
    {
      "civico": "34",
      "barrato": "G"
    },
    {
      "civico": "34",
      "barrato": "H"
    },
    {
      "civico": "34",
      "barrato": "I"
    },
    {
      "civico": "34",
      "barrato": "L"
    },
    {
      "civico": "34",
      "barrato": "M"
    },
    {
      "civico": "34",
      "barrato": "N"
    },
    {
      "civico": "34",
      "barrato": null
    },
    {
      "civico": "36",
      "barrato": null
    },
    {
      "civico": "53",
      "barrato": null
    },
    {
      "civico": "56",
      "barrato": null
    },
    {
      "civico": "58",
      "barrato": null
    },
    {
      "civico": "60",
      "barrato": null
    },
    {
      "civico": "62",
      "barrato": "A"
    },
    {
      "civico": "62",
      "barrato": null
    },
    {
      "civico": "64",
      "barrato": null
    },
    {
      "civico": "66",
      "barrato": null
    },
    {
      "civico": "84",
      "barrato": null
    }
  ],
  "VIA GENERALE CARLO ALBERTO DALLA CHIESA": [
    {
      "civico": "2",
      "barrato": null
    }
  ],
  "VIA IMPRUNETANA PER POZZOLATICO": [
    {
      "civico": "60",
      "barrato": "A"
    },
    {
      "civico": "95",
      "barrato": null
    },
    {
      "civico": "97",
      "barrato": "A"
    },
    {
      "civico": "97",
      "barrato": "B"
    },
    {
      "civico": "142",
      "barrato": "P"
    },
    {
      "civico": "163",
      "barrato": null
    },
    {
      "civico": "165",
      "barrato": null
    },
    {
      "civico": "218",
      "barrato": null
    },
    {
      "civico": "220",
      "barrato": null
    },
    {
      "civico": "222",
      "barrato": null
    },
    {
      "civico": "226",
      "barrato": null
    },
    {
      "civico": "228",
      "barrato": null
    },
    {
      "civico": "230",
      "barrato": null
    },
    {
      "civico": "232",
      "barrato": null
    },
    {
      "civico": "234",
      "barrato": null
    },
    {
      "civico": "236",
      "barrato": null
    },
    {
      "civico": "238",
      "barrato": null
    },
    {
      "civico": "240",
      "barrato": null
    },
    {
      "civico": "242",
      "barrato": null
    }
  ],
  "VIA IMPRUNETANA PER TAVARNUZZE": [
    {
      "civico": "66",
      "barrato": null
    },
    {
      "civico": "68",
      "barrato": null
    },
    {
      "civico": "75",
      "barrato": null
    },
    {
      "civico": "85",
      "barrato": "A"
    },
    {
      "civico": "86",
      "barrato": null
    },
    {
      "civico": "88",
      "barrato": null
    },
    {
      "civico": "90",
      "barrato": null
    },
    {
      "civico": "92",
      "barrato": "A"
    },
    {
      "civico": "92",
      "barrato": "B"
    },
    {
      "civico": "92",
      "barrato": "C"
    },
    {
      "civico": "92",
      "barrato": null
    },
    {
      "civico": "94",
      "barrato": null
    },
    {
      "civico": "96",
      "barrato": null
    },
    {
      "civico": "98",
      "barrato": null
    },
    {
      "civico": "100",
      "barrato": null
    },
    {
      "civico": "102",
      "barrato": null
    },
    {
      "civico": "104",
      "barrato": null
    },
    {
      "civico": "106",
      "barrato": null
    },
    {
      "civico": "191",
      "barrato": null
    },
    {
      "civico": "193",
      "barrato": null
    },
    {
      "civico": "211",
      "barrato": null
    },
    {
      "civico": "213",
      "barrato": null
    },
    {
      "civico": "215",
      "barrato": "A"
    },
    {
      "civico": "215",
      "barrato": "B"
    },
    {
      "civico": "215",
      "barrato": null
    },
    {
      "civico": "217",
      "barrato": null
    },
    {
      "civico": "219",
      "barrato": null
    },
    {
      "civico": "221",
      "barrato": null
    },
    {
      "civico": "223",
      "barrato": null
    }
  ],
  "VIA LANCIOLA": [
    {
      "civico": "1",
      "barrato": null
    },
    {
      "civico": "2",
      "barrato": null
    },
    {
      "civico": "4",
      "barrato": null
    },
    {
      "civico": "8",
      "barrato": null
    }
  ],
  "VIA LUIGIANA": [
    {
      "civico": "1",
      "barrato": null
    },
    {
      "civico": "4",
      "barrato": "A"
    },
    {
      "civico": "5",
      "barrato": "A"
    },
    {
      "civico": "6",
      "barrato": null
    },
    {
      "civico": "20",
      "barrato": null
    },
    {
      "civico": "21",
      "barrato": null
    },
    {
      "civico": "23",
      "barrato": "A"
    },
    {
      "civico": "23",
      "barrato": null
    },
    {
      "civico": "25",
      "barrato": "A"
    },
    {
      "civico": "25",
      "barrato": null
    },
    {
      "civico": "30",
      "barrato": null
    }
  ],
  "VIA MATTEONI": [
    {
      "civico": "1",
      "barrato": null
    },
    {
      "civico": "2",
      "barrato": "A"
    },
    {
      "civico": "2",
      "barrato": "B"
    },
    {
      "civico": "4",
      "barrato": null
    },
    {
      "civico": "5",
      "barrato": null
    },
    {
      "civico": "6",
      "barrato": null
    },
    {
      "civico": "7",
      "barrato": null
    },
    {
      "civico": "8",
      "barrato": null
    },
    {
      "civico": "9",
      "barrato": null
    },
    {
      "civico": "11",
      "barrato": null
    },
    {
      "civico": "12",
      "barrato": null
    },
    {
      "civico": "13",
      "barrato": null
    },
    {
      "civico": "15",
      "barrato": null
    },
    {
      "civico": "17",
      "barrato": null
    }
  ],
  "VIA MONTAUTO": [
    {
      "civico": "0",
      "barrato": null
    },
    {
      "civico": "1",
      "barrato": "C"
    }
  ],
  "VIA MONTEBUONI": [
    {
      "civico": "1",
      "barrato": null
    },
    {
      "civico": "2",
      "barrato": "A"
    },
    {
      "civico": "3",
      "barrato": null
    },
    {
      "civico": "5",
      "barrato": null
    },
    {
      "civico": "7",
      "barrato": null
    },
    {
      "civico": "9",
      "barrato": null
    },
    {
      "civico": "10",
      "barrato": null
    },
    {
      "civico": "12",
      "barrato": "M"
    },
    {
      "civico": "12",
      "barrato": null
    },
    {
      "civico": "14",
      "barrato": null
    },
    {
      "civico": "16",
      "barrato": null
    },
    {
      "civico": "18",
      "barrato": null
    },
    {
      "civico": "35",
      "barrato": null
    },
    {
      "civico": "37",
      "barrato": null
    },
    {
      "civico": "39",
      "barrato": null
    },
    {
      "civico": "41",
      "barrato": "A"
    },
    {
      "civico": "41",
      "barrato": "H"
    },
    {
      "civico": "41",
      "barrato": "M"
    },
    {
      "civico": "41",
      "barrato": "N"
    },
    {
      "civico": "41",
      "barrato": "O"
    },
    {
      "civico": "41",
      "barrato": null
    },
    {
      "civico": "43",
      "barrato": null
    },
    {
      "civico": "45",
      "barrato": null
    },
    {
      "civico": "75",
      "barrato": null
    },
    {
      "civico": "83",
      "barrato": null
    },
    {
      "civico": "87",
      "barrato": null
    },
    {
      "civico": "89",
      "barrato": null
    },
    {
      "civico": "91",
      "barrato": null
    },
    {
      "civico": "93",
      "barrato": null
    },
    {
      "civico": "95",
      "barrato": null
    }
  ],
  "VIA NIZZANO": [
    {
      "civico": "1",
      "barrato": "A"
    },
    {
      "civico": "1",
      "barrato": "B"
    }
  ],
  "VIA PIAN DI PANCOLE": [
    {
      "civico": "1",
      "barrato": null
    },
    {
      "civico": "3",
      "barrato": null
    }
  ],
  "VIA POGGIOSECCO": [
    {
      "civico": "0",
      "barrato": null
    },
    {
      "civico": "9",
      "barrato": "D"
    },
    {
      "civico": "23",
      "barrato": null
    }
  ],
  "VIA PONTE A IOZZI": [
    {
      "civico": "0",
      "barrato": "SNC"
    },
    {
      "civico": "0",
      "barrato": null
    },
    {
      "civico": "4",
      "barrato": null
    }
  ],
  "VIA QUINTOLE PER LE ROSE": [
    {
      "civico": "62",
      "barrato": null
    },
    {
      "civico": "66",
      "barrato": null
    },
    {
      "civico": "68",
      "barrato": null
    },
    {
      "civico": "113",
      "barrato": null
    },
    {
      "civico": "121",
      "barrato": null
    },
    {
      "civico": "123",
      "barrato": "A"
    },
    {
      "civico": "123",
      "barrato": null
    },
    {
      "civico": "125",
      "barrato": null
    },
    {
      "civico": "127",
      "barrato": null
    },
    {
      "civico": "129",
      "barrato": "A"
    },
    {
      "civico": "129",
      "barrato": null
    },
    {
      "civico": "131",
      "barrato": null
    },
    {
      "civico": "141",
      "barrato": null
    },
    {
      "civico": "143",
      "barrato": null
    },
    {
      "civico": "145",
      "barrato": null
    },
    {
      "civico": "147",
      "barrato": null
    },
    {
      "civico": "149",
      "barrato": null
    },
    {
      "civico": "151",
      "barrato": null
    },
    {
      "civico": "153",
      "barrato": null
    },
    {
      "civico": "155",
      "barrato": null
    },
    {
      "civico": "159",
      "barrato": null
    }
  ],
  "VIA ROMA": [
    {
      "civico": "48",
      "barrato": null
    },
    {
      "civico": "50",
      "barrato": null
    },
    {
      "civico": "52",
      "barrato": "A"
    },
    {
      "civico": "52",
      "barrato": "B"
    },
    {
      "civico": "52",
      "barrato": null
    }
  ],
  "VIA SAN CRISTOFANO": [
    {
      "civico": "0",
      "barrato": null
    },
    {
      "civico": "13",
      "barrato": null
    }
  ],
  "VIA TAFANI": [
    {
      "civico": "0",
      "barrato": null
    },
    {
      "civico": "2",
      "barrato": "A"
    },
    {
      "civico": "2",
      "barrato": "B"
    },
    {
      "civico": "2",
      "barrato": "C"
    },
    {
      "civico": "2",
      "barrato": "D"
    },
    {
      "civico": "2",
      "barrato": "E"
    },
    {
      "civico": "2",
      "barrato": "F"
    },
    {
      "civico": "2",
      "barrato": "G"
    },
    {
      "civico": "2",
      "barrato": "H"
    },
    {
      "civico": "2",
      "barrato": "I"
    },
    {
      "civico": "3",
      "barrato": "B"
    },
    {
      "civico": "3",
      "barrato": "C"
    },
    {
      "civico": "3",
      "barrato": null
    },
    {
      "civico": "5",
      "barrato": null
    },
    {
      "civico": "6",
      "barrato": null
    },
    {
      "civico": "7",
      "barrato": null
    },
    {
      "civico": "8",
      "barrato": null
    },
    {
      "civico": "10",
      "barrato": "A"
    },
    {
      "civico": "10",
      "barrato": "B"
    },
    {
      "civico": "10",
      "barrato": null
    },
    {
      "civico": "11",
      "barrato": null
    },
    {
      "civico": "12",
      "barrato": null
    },
    {
      "civico": "13",
      "barrato": null
    },
    {
      "civico": "14",
      "barrato": null
    },
    {
      "civico": "20",
      "barrato": null
    }
  ],
  "VIA TORRICELLA": [
    {
      "civico": "14",
      "barrato": null
    },
    {
      "civico": "16",
      "barrato": "A"
    },
    {
      "civico": "16",
      "barrato": "B"
    },
    {
      "civico": "16",
      "barrato": null
    },
    {
      "civico": "22",
      "barrato": null
    }
  ],
  "VIA VOLTERRANA": [
    {
      "civico": "7",
      "barrato": "A"
    },
    {
      "civico": "8",
      "barrato": null
    },
    {
      "civico": "10",
      "barrato": null
    },
    {
      "civico": "12",
      "barrato": null
    },
    {
      "civico": "23",
      "barrato": null
    },
    {
      "civico": "27",
      "barrato": "A"
    },
    {
      "civico": "29",
      "barrato": "A"
    },
    {
      "civico": "51",
      "barrato": "A"
    }
  ],
  "VIALE VITTORIO VENETO": [
    {
      "civico": "38",
      "barrato": null
    },
    {
      "civico": "39",
      "barrato": null
    },
    {
      "civico": "41",
      "barrato": "A"
    },
    {
      "civico": "41",
      "barrato": "H"
    },
    {
      "civico": "41",
      "barrato": null
    },
    {
      "civico": "43",
      "barrato": null
    }
  ],
  "VICOLO DELLE ROSE": [
    {
      "civico": "9",
      "barrato": null
    }
  ]
}