{
  "LOCALITA' CASARIGO": [
    {
      "civico": "1",
      "barrato": null
    }
  ],
  "PIAZZETTA PERTEVANO": [
    {
      "civico": "1",
      "barrato": null
    },
    {
      "civico": "2",
      "barrato": null
    },
    {
      "civico": "3",
      "barrato": null
    },
    {
      "civico": "4",
      "barrato": null
    },
    {
      "civico": "6",
      "barrato": null
    },
    {
      "civico": "8",
      "barrato": null
    },
    {
      "civico": "10",
      "barrato": null
    }
  ],
  "VIA ALTA COLLINA": [
    {
      "civico": "41",
      "barrato": "A"
    },
    {
      "civico": "55",
      "barrato": null
    },
    {
      "civico": "57",
      "barrato": null
    },
    {
      "civico": "58",
      "barrato": null
    }
  ],
  "VIA DEI CARPINI": [
    {
      "civico": "47",
      "barrato": null
    }
  ],
  "VIA DEL BELSEDERE": [
    {
      "civico": "9",
      "barrato": "A"
    },
    {
      "civico": "13",
      "barrato": null
    },
    {
      "civico": "17",
      "barrato": null
    }
  ],
  "VIA DEL CERESE'": [
    {
      "civico": "3",
      "barrato": "A"
    },
    {
      "civico": "9",
      "barrato": "A"
    },
    {
      "civico": "9",
      "barrato": "B"
    }
  ],
  "VIA DEL PERTEVANO": [
    {
      "civico": "1",
      "barrato": null
    },
    {
      "civico": "2",
      "barrato": null
    },
    {
      "civico": "3",
      "barrato": "A"
    },
    {
      "civico": "3",
      "barrato": null
    },
    {
      "civico": "4",
      "barrato": null
    },
    {
      "civico": "6",
      "barrato": null
    },
    {
      "civico": "8",
      "barrato": null
    },
    {
      "civico": "13",
      "barrato": null
    },
    {
      "civico": "24",
      "barrato": "A"
    }
  ],
  "VIA DELLE ROBINIE": [
    {
      "civico": "2",
      "barrato": "A"
    }
  ],
  "VIA DELLE SORGENTI": [
    {
      "civico": "39",
      "barrato": null
    },
    {
      "civico": "41",
      "barrato": "A"
    },
    {
      "civico": "44",
      "barrato": "A"
    },
    {
      "civico": "44",
      "barrato": "B"
    },
    {
      "civico": "49",
      "barrato": "A"
    },
    {
      "civico": "51",
      "barrato": null
    },
    {
      "civico": "52",
      "barrato": null
    }
  ],
  "VIA OSTIZZA": [
    {
      "civico": "7",
      "barrato": "B"
    },
    {
      "civico": "8",
      "barrato": "B"
    },
    {
      "civico": "8",
      "barrato": "C"
    },
    {
      "civico": "12",
      "barrato": null
    },
    {
      "civico": "15",
      "barrato": null
    }
  ],
  "VIA PASSONE": [
    {
      "civico": "2",
      "barrato": null
    }
  ],
  "VIA PRIVATA CAMPE'": [
    {
      "civico": "1",
      "barrato": null
    },
    {
      "civico": "3",
      "barrato": null
    },
    {
      "civico": "4",
      "barrato": "A"
    },
    {
      "civico": "8",
      "barrato": "A"
    },
    {
      "civico": "14",
      "barrato": null
    }
  ],
  "VIA PRIVATA PERTEVANO": [
    {
      "civico": "1",
      "barrato": null
    },
    {
      "civico": "2",
      "barrato": null
    },
    {
      "civico": "3",
      "barrato": null
    },
    {
      "civico": "4",
      "barrato": null
    },
    {
      "civico": "5",
      "barrato": null
    },
    {
      "civico": "6",
      "barrato": null
    },
    {
      "civico": "8",
      "barrato": null
    },
    {
      "civico": "9",
      "barrato": null
    },
    {
      "civico": "10",
      "barrato": null
    },
    {
      "civico": "11",
      "barrato": null
    },
    {
      "civico": "12",
      "barrato": null
    },
    {
      "civico": "13",
      "barrato": null
    },
    {
      "civico": "15",
      "barrato": null
    },
    {
      "civico": "19",
      "barrato": null
    },
    {
      "civico": "21",
      "barrato": null
    },
    {
      "civico": "23",
      "barrato": null
    },
    {
      "civico": "25",
      "barrato": null
    }
  ],
  "VIA PRIVATA SPIAZZOLO": [
    {
      "civico": "21",
      "barrato": "A"
    },
    {
      "civico": "25",
      "barrato": "A"
    }
  ]
}