{
  "LOCALITA' PUNTINE": [
    {
      "civico": "3",
      "barrato": null
    }
  ],
  "PIAZZA ALDO MORO": [
    {
      "civico": "0",
      "barrato": null
    },
    {
      "civico": "7",
      "barrato": "3"
    },
    {
      "civico": "13",
      "barrato": null
    },
    {
      "civico": "15",
      "barrato": "1"
    }
  ],
  "PIAZZALE DONATORI DI SANGUE": [
    {
      "civico": "0",
      "barrato": null
    },
    {
      "civico": "3",
      "barrato": null
    }
  ],
  "STRADA ALTA BELVEDERE": [
    {
      "civico": "3",
      "barrato": "1"
    },
    {
      "civico": "5",
      "barrato": null
    },
    {
      "civico": "6",
      "barrato": null
    }
  ],
  "STRADA BASSA MALVEZZO": [
    {
      "civico": "2",
      "barrato": "15"
    },
    {
      "civico": "2",
      "barrato": "19"
    },
    {
      "civico": "2",
      "barrato": "17"
    },
    {
      "civico": "2",
      "barrato": "20"
    }
  ],
  "STRADA BOCCALINA": [
    {
      "civico": "6",
      "barrato": "A"
    },
    {
      "civico": "8",
      "barrato": "10"
    },
    {
      "civico": "10",
      "barrato": null
    }
  ],
  "STRADA CASTELLETTO": [
    {
      "civico": "13",
      "barrato": null
    },
    {
      "civico": "19",
      "barrato": null
    },
    {
      "civico": "49",
      "barrato": null
    },
    {
      "civico": "56",
      "barrato": "2"
    }
  ],
  "STRADA COLONNE": [
    {
      "civico": "4",
      "barrato": null
    },
    {
      "civico": "23",
      "barrato": "1"
    }
  ],
  "STRADA DOSSI": [
    {
      "civico": "0",
      "barrato": null
    },
    {
      "civico": "3",
      "barrato": null
    },
    {
      "civico": "4",
      "barrato": null
    },
    {
      "civico": "5",
      "barrato": null
    },
    {
      "civico": "13",
      "barrato": "11"
    },
    {
      "civico": "13",
      "barrato": "23"
    },
    {
      "civico": "17",
      "barrato": "11"
    },
    {
      "civico": "20",
      "barrato": null
    },
    {
      "civico": "21",
      "barrato": "1"
    },
    {
      "civico": "21",
      "barrato": "10"
    },
    {
      "civico": "21",
      "barrato": "18"
    },
    {
      "civico": "21",
      "barrato": "20"
    },
    {
      "civico": "22",
      "barrato": null
    },
    {
      "civico": "23",
      "barrato": null
    },
    {
      "civico": "24",
      "barrato": null
    },
    {
      "civico": "28",
      "barrato": null
    },
    {
      "civico": "30",
      "barrato": null
    },
    {
      "civico": "32",
      "barrato": null
    },
    {
      "civico": "34",
      "barrato": null
    },
    {
      "civico": "36",
      "barrato": null
    },
    {
      "civico": "38",
      "barrato": null
    },
    {
      "civico": "46",
      "barrato": null
    },
    {
      "civico": "52",
      "barrato": null
    }
  ],
  "STRADA LEVATA": [
    {
      "civico": "9",
      "barrato": "1"
    }
  ],
  "STRADA MANDRAGO": [
    {
      "civico": "11",
      "barrato": null
    },
    {
      "civico": "12",
      "barrato": null
    },
    {
      "civico": "17",
      "barrato": null
    },
    {
      "civico": "18",
      "barrato": null
    },
    {
      "civico": "19",
      "barrato": "A"
    },
    {
      "civico": "19",
      "barrato": "H"
    },
    {
      "civico": "19",
      "barrato": "I"
    },
    {
      "civico": "19",
      "barrato": null
    },
    {
      "civico": "21",
      "barrato": null
    },
    {
      "civico": "32",
      "barrato": null
    },
    {
      "civico": "39",
      "barrato": null
    },
    {
      "civico": "41",
      "barrato": null
    }
  ],
  "STRADA MEDEA": [
    {
      "civico": "0",
      "barrato": null
    }
  ],
  "STRADA ORMEDELLO": [
    {
      "civico": "8",
      "barrato": "1"
    },
    {
      "civico": "13",
      "barrato": null
    },
    {
      "civico": "14",
      "barrato": "BIS"
    },
    {
      "civico": "14",
      "barrato": null
    },
    {
      "civico": "15",
      "barrato": null
    },
    {
      "civico": "16",
      "barrato": "3"
    },
    {
      "civico": "16",
      "barrato": null
    },
    {
      "civico": "18",
      "barrato": "1"
    },
    {
      "civico": "18",
      "barrato": null
    },
    {
      "civico": "20",
      "barrato": null
    },
    {
      "civico": "25",
      "barrato": "1"
    },
    {
      "civico": "25",
      "barrato": "2"
    },
    {
      "civico": "25",
      "barrato": "4"
    },
    {
      "civico": "25",
      "barrato": null
    },
    {
      "civico": "27",
      "barrato": null
    },
    {
      "civico": "29",
      "barrato": null
    },
    {
      "civico": "33",
      "barrato": null
    },
    {
      "civico": "37",
      "barrato": "1"
    }
  ],
  "STRADA POZZOLO": [
    {
      "civico": "1",
      "barrato": "BIS"
    }
  ],
  "STRADA SANTA LUCIA": [
    {
      "civico": "7",
      "barrato": "A"
    },
    {
      "civico": "7",
      "barrato": "B"
    }
  ],
  "STRADA STATALE 249 NORD": [
    {
      "civico": "1",
      "barrato": "A 1"
    },
    {
      "civico": "1",
      "barrato": "A 2"
    },
    {
      "civico": "3",
      "barrato": "1"
    },
    {
      "civico": "5",
      "barrato": "2 A"
    },
    {
      "civico": "5",
      "barrato": null
    },
    {
      "civico": "12",
      "barrato": "4 A"
    },
    {
      "civico": "12",
      "barrato": "4 B"
    },
    {
      "civico": "18",
      "barrato": "1"
    }
  ],
  "STRADA STATALE 62 NORD": [
    {
      "civico": "18",
      "barrato": "1"
    }
  ],
  "STRADA STATALE 62 SUD": [
    {
      "civico": "0",
      "barrato": null
    },
    {
      "civico": "2",
      "barrato": "2 A"
    },
    {
      "civico": "4",
      "barrato": null
    },
    {
      "civico": "11",
      "barrato": null
    },
    {
      "civico": "14",
      "barrato": null
    }
  ],
  "TRASVERSALE SANTA LUCIA": [
    {
      "civico": "0",
      "barrato": null
    }
  ],
  "VIA ANDREA DORIA": [
    {
      "civico": "9",
      "barrato": "1"
    }
  ],
  "VIA CORTE BERTOLA": [
    {
      "civico": "23",
      "barrato": null
    },
    {
      "civico": "34",
      "barrato": "2 A"
    },
    {
      "civico": "34",
      "barrato": "2 C"
    },
    {
      "civico": "34",
      "barrato": "2"
    },
    {
      "civico": "34",
      "barrato": null
    }
  ],
  "VIA PIAVE": [
    {
      "civico": "191",
      "barrato": "C"
    }
  ],
  "VIA RITA LEVI MONTALCINI": [
    {
      "civico": "3",
      "barrato": null
    }
  ]
}