{
  "BORGO RINASCITA": [
    {
      "civico": "64",
      "barrato": null
    }
  ],
  "PIAZZALE DEL POPOLO": [
    {
      "civico": "23",
      "barrato": "E"
    }
  ],
  "STRADA STATALE 16": [
    {
      "civico": "640",
      "barrato": "F"
    },
    {
      "civico": "701",
      "barrato": null
    },
    {
      "civico": "705",
      "barrato": null
    },
    {
      "civico": "903",
      "barrato": "A"
    },
    {
      "civico": "903",
      "barrato": "B"
    },
    {
      "civico": "1255",
      "barrato": null
    },
    {
      "civico": "1878",
      "barrato": null
    },
    {
      "civico": "1929",
      "barrato": null
    },
    {
      "civico": "1954",
      "barrato": null
    },
    {
      "civico": "1956",
      "barrato": null
    },
    {
      "civico": "2065",
      "barrato": null
    },
    {
      "civico": "2209",
      "barrato": "1"
    },
    {
      "civico": "2209",
      "barrato": "2"
    },
    {
      "civico": "2209",
      "barrato": null
    },
    {
      "civico": "2212",
      "barrato": "A"
    },
    {
      "civico": "2216",
      "barrato": "D"
    },
    {
      "civico": "2218",
      "barrato": "A"
    },
    {
      "civico": "2218",
      "barrato": "B"
    },
    {
      "civico": "2218",
      "barrato": "C"
    },
    {
      "civico": "2218",
      "barrato": "D"
    },
    {
      "civico": "2218",
      "barrato": "E"
    },
    {
      "civico": "2218",
      "barrato": "F"
    },
    {
      "civico": "2218",
      "barrato": "G"
    },
    {
      "civico": "2218",
      "barrato": null
    },
    {
      "civico": "2287",
      "barrato": "B"
    },
    {
      "civico": "2287",
      "barrato": "C"
    },
    {
      "civico": "2287",
      "barrato": "D"
    },
    {
      "civico": "2287",
      "barrato": "E"
    },
    {
      "civico": "2287",
      "barrato": null
    },
    {
      "civico": "2327",
      "barrato": "A"
    },
    {
      "civico": "2327",
      "barrato": "D"
    },
    {
      "civico": "2426",
      "barrato": null
    },
    {
      "civico": "2502",
      "barrato": "D"
    },
    {
      "civico": "2762",
      "barrato": "A"
    },
    {
      "civico": "2976",
      "barrato": "A"
    },
    {
      "civico": "3008",
      "barrato": "A"
    },
    {
      "civico": "3008",
      "barrato": "B"
    },
    {
      "civico": "3008",
      "barrato": "C"
    },
    {
      "civico": "3491",
      "barrato": "A"
    },
    {
      "civico": "3491",
      "barrato": "E"
    },
    {
      "civico": "3491",
      "barrato": "F"
    },
    {
      "civico": "3508",
      "barrato": "E"
    },
    {
      "civico": "3577",
      "barrato": "A"
    },
    {
      "civico": "3577",
      "barrato": "B"
    },
    {
      "civico": "3588",
      "barrato": null
    },
    {
      "civico": "4181",
      "barrato": "A"
    },
    {
      "civico": "4181",
      "barrato": "B"
    },
    {
      "civico": "4181",
      "barrato": null
    },
    {
      "civico": "4198",
      "barrato": "A"
    },
    {
      "civico": "4198",
      "barrato": "B"
    },
    {
      "civico": "4198",
      "barrato": null
    }
  ],
  "VIA ALESSANDRO SELMI": [
    {
      "civico": "65",
      "barrato": null
    },
    {
      "civico": "155",
      "barrato": null
    },
    {
      "civico": "157",
      "barrato": null
    },
    {
      "civico": "161",
      "barrato": null
    },
    {
      "civico": "163",
      "barrato": null
    },
    {
      "civico": "165",
      "barrato": null
    },
    {
      "civico": "167",
      "barrato": null
    },
    {
      "civico": "169",
      "barrato": null
    },
    {
      "civico": "171",
      "barrato": null
    },
    {
      "civico": "173",
      "barrato": null
    },
    {
      "civico": "175",
      "barrato": null
    },
    {
      "civico": "189",
      "barrato": "A 1"
    },
    {
      "civico": "189",
      "barrato": "A 2"
    },
    {
      "civico": "189",
      "barrato": "A 3"
    },
    {
      "civico": "189",
      "barrato": "A 5"
    },
    {
      "civico": "189",
      "barrato": "A 6"
    },
    {
      "civico": "189",
      "barrato": "A 7"
    },
    {
      "civico": "189",
      "barrato": "A 8"
    },
    {
      "civico": "189",
      "barrato": "B 1"
    },
    {
      "civico": "189",
      "barrato": "B 2"
    },
    {
      "civico": "189",
      "barrato": "I 1"
    },
    {
      "civico": "189",
      "barrato": "I 2"
    },
    {
      "civico": "543",
      "barrato": null
    },
    {
      "civico": "966",
      "barrato": null
    }
  ],
  "VIA BRESPAROLA": [
    {
      "civico": "0",
      "barrato": null
    },
    {
      "civico": "735",
      "barrato": null
    },
    {
      "civico": "825",
      "barrato": null
    },
    {
      "civico": "879",
      "barrato": null
    },
    {
      "civico": "911",
      "barrato": null
    },
    {
      "civico": "933",
      "barrato": null
    },
    {
      "civico": "1203",
      "barrato": null
    },
    {
      "civico": "2655",
      "barrato": null
    },
    {
      "civico": "2711",
      "barrato": null
    },
    {
      "civico": "2737",
      "barrato": null
    },
    {
      "civico": "2741",
      "barrato": null
    },
    {
      "civico": "2771",
      "barrato": null
    },
    {
      "civico": "2773",
      "barrato": null
    },
    {
      "civico": "2881",
      "barrato": null
    },
    {
      "civico": "2899",
      "barrato": null
    }
  ],
  "VIA CORONELLA": [
    {
      "civico": "62",
      "barrato": "D"
    },
    {
      "civico": "69",
      "barrato": null
    },
    {
      "civico": "71",
      "barrato": null
    },
    {
      "civico": "73",
      "barrato": null
    }
  ],
  "VIA DEL GORGO": [
    {
      "civico": "0",
      "barrato": null
    }
  ],
  "VIA DEL LAVORO": [
    {
      "civico": "0",
      "barrato": null
    },
    {
      "civico": "94",
      "barrato": null
    },
    {
      "civico": "114",
      "barrato": null
    },
    {
      "civico": "116",
      "barrato": null
    },
    {
      "civico": "118",
      "barrato": null
    },
    {
      "civico": "120",
      "barrato": null
    },
    {
      "civico": "122",
      "barrato": null
    },
    {
      "civico": "124",
      "barrato": null
    },
    {
      "civico": "126",
      "barrato": "A"
    },
    {
      "civico": "126",
      "barrato": null
    },
    {
      "civico": "151",
      "barrato": null
    },
    {
      "civico": "200",
      "barrato": null
    },
    {
      "civico": "220",
      "barrato": null
    },
    {
      "civico": "221",
      "barrato": null
    },
    {
      "civico": "271",
      "barrato": null
    },
    {
      "civico": "290",
      "barrato": "A"
    },
    {
      "civico": "290",
      "barrato": "B"
    },
    {
      "civico": "290",
      "barrato": null
    },
    {
      "civico": "300",
      "barrato": "A"
    },
    {
      "civico": "300",
      "barrato": "B"
    },
    {
      "civico": "300",
      "barrato": null
    },
    {
      "civico": "328",
      "barrato": "A"
    },
    {
      "civico": "328",
      "barrato": "B"
    },
    {
      "civico": "328",
      "barrato": null
    },
    {
      "civico": "330",
      "barrato": null
    },
    {
      "civico": "332",
      "barrato": null
    },
    {
      "civico": "334",
      "barrato": null
    },
    {
      "civico": "336",
      "barrato": null
    },
    {
      "civico": "338",
      "barrato": null
    },
    {
      "civico": "340",
      "barrato": null
    },
    {
      "civico": "342",
      "barrato": null
    },
    {
      "civico": "346",
      "barrato": null
    },
    {
      "civico": "348",
      "barrato": null
    },
    {
      "civico": "350",
      "barrato": null
    },
    {
      "civico": "352",
      "barrato": null
    },
    {
      "civico": "354",
      "barrato": null
    },
    {
      "civico": "356",
      "barrato": null
    },
    {
      "civico": "358",
      "barrato": null
    },
    {
      "civico": "360",
      "barrato": null
    },
    {
      "civico": "362",
      "barrato": null
    },
    {
      "civico": "364",
      "barrato": null
    },
    {
      "civico": "366",
      "barrato": null
    },
    {
      "civico": "368",
      "barrato": null
    },
    {
      "civico": "370",
      "barrato": null
    },
    {
      "civico": "372",
      "barrato": null
    },
    {
      "civico": "374",
      "barrato": null
    },
    {
      "civico": "376",
      "barrato": null
    },
    {
      "civico": "378",
      "barrato": null
    },
    {
      "civico": "380",
      "barrato": null
    },
    {
      "civico": "382",
      "barrato": null
    },
    {
      "civico": "384",
      "barrato": null
    },
    {
      "civico": "386",
      "barrato": null
    },
    {
      "civico": "388",
      "barrato": null
    },
    {
      "civico": "390",
      "barrato": null
    },
    {
      "civico": "392",
      "barrato": null
    },
    {
      "civico": "394",
      "barrato": null
    },
    {
      "civico": "395",
      "barrato": null
    },
    {
      "civico": "396",
      "barrato": null
    },
    {
      "civico": "398",
      "barrato": null
    },
    {
      "civico": "400",
      "barrato": null
    },
    {
      "civico": "402",
      "barrato": null
    },
    {
      "civico": "404",
      "barrato": null
    },
    {
      "civico": "406",
      "barrato": null
    },
    {
      "civico": "408",
      "barrato": null
    },
    {
      "civico": "410",
      "barrato": null
    },
    {
      "civico": "412",
      "barrato": null
    },
    {
      "civico": "414",
      "barrato": null
    },
    {
      "civico": "416",
      "barrato": null
    },
    {
      "civico": "418",
      "barrato": null
    },
    {
      "civico": "420",
      "barrato": null
    },
    {
      "civico": "422",
      "barrato": null
    },
    {
      "civico": "424",
      "barrato": null
    },
    {
      "civico": "426",
      "barrato": null
    },
    {
      "civico": "580",
      "barrato": null
    },
    {
      "civico": "658",
      "barrato": null
    },
    {
      "civico": "660",
      "barrato": null
    }
  ],
  "VIA DON GIOVANNI MINZONI": [
    {
      "civico": "482",
      "barrato": "A"
    },
    {
      "civico": "482",
      "barrato": "B"
    },
    {
      "civico": "482",
      "barrato": "C"
    },
    {
      "civico": "482",
      "barrato": null
    },
    {
      "civico": "498",
      "barrato": null
    },
    {
      "civico": "500",
      "barrato": null
    },
    {
      "civico": "502",
      "barrato": null
    },
    {
      "civico": "504",
      "barrato": null
    },
    {
      "civico": "506",
      "barrato": null
    },
    {
      "civico": "510",
      "barrato": null
    },
    {
      "civico": "512",
      "barrato": null
    }
  ],
  "VIA DUE MARTIRI": [
    {
      "civico": "0",
      "barrato": null
    },
    {
      "civico": "1",
      "barrato": null
    },
    {
      "civico": "2",
      "barrato": null
    },
    {
      "civico": "3",
      "barrato": null
    },
    {
      "civico": "4",
      "barrato": "A"
    },
    {
      "civico": "4",
      "barrato": null
    },
    {
      "civico": "5",
      "barrato": "A"
    },
    {
      "civico": "5",
      "barrato": "B"
    },
    {
      "civico": "5",
      "barrato": null
    },
    {
      "civico": "68",
      "barrato": null
    },
    {
      "civico": "654",
      "barrato": null
    },
    {
      "civico": "1102",
      "barrato": null
    },
    {
      "civico": "1136",
      "barrato": "A"
    },
    {
      "civico": "1226",
      "barrato": null
    },
    {
      "civico": "1488",
      "barrato": null
    },
    {
      "civico": "1634",
      "barrato": null
    },
    {
      "civico": "2234",
      "barrato": null
    },
    {
      "civico": "2288",
      "barrato": null
    },
    {
      "civico": "2816",
      "barrato": "A"
    },
    {
      "civico": "2816",
      "barrato": "B"
    },
    {
      "civico": "3196",
      "barrato": null
    },
    {
      "civico": "3558",
      "barrato": null
    },
    {
      "civico": "3568",
      "barrato": null
    }
  ],
  "VIA ENZO FERRARI": [
    {
      "civico": "16",
      "barrato": null
    },
    {
      "civico": "18",
      "barrato": null
    },
    {
      "civico": "30",
      "barrato": null
    },
    {
      "civico": "55",
      "barrato": "B"
    },
    {
      "civico": "55",
      "barrato": "C"
    },
    {
      "civico": "55",
      "barrato": null
    },
    {
      "civico": "63",
      "barrato": null
    },
    {
      "civico": "71",
      "barrato": null
    },
    {
      "civico": "94",
      "barrato": null
    },
    {
      "civico": "101",
      "barrato": "A"
    },
    {
      "civico": "101",
      "barrato": "B"
    },
    {
      "civico": "101",
      "barrato": "C"
    },
    {
      "civico": "101",
      "barrato": null
    },
    {
      "civico": "106",
      "barrato": null
    },
    {
      "civico": "109",
      "barrato": null
    },
    {
      "civico": "111",
      "barrato": "B"
    },
    {
      "civico": "116",
      "barrato": null
    },
    {
      "civico": "119",
      "barrato": null
    },
    {
      "civico": "136",
      "barrato": "A"
    },
    {
      "civico": "136",
      "barrato": "B"
    },
    {
      "civico": "136",
      "barrato": null
    },
    {
      "civico": "147",
      "barrato": null
    },
    {
      "civico": "152",
      "barrato": null
    },
    {
      "civico": "161",
      "barrato": null
    },
    {
      "civico": "171",
      "barrato": "A"
    },
    {
      "civico": "171",
      "barrato": "B"
    },
    {
      "civico": "171",
      "barrato": null
    },
    {
      "civico": "176",
      "barrato": "A"
    },
    {
      "civico": "176",
      "barrato": "B"
    },
    {
      "civico": "176",
      "barrato": null
    },
    {
      "civico": "177",
      "barrato": "A"
    },
    {
      "civico": "177",
      "barrato": null
    },
    {
      "civico": "187",
      "barrato": null
    },
    {
      "civico": "195",
      "barrato": "A"
    },
    {
      "civico": "195",
      "barrato": null
    },
    {
      "civico": "205",
      "barrato": null
    },
    {
      "civico": "210",
      "barrato": "A"
    },
    {
      "civico": "210",
      "barrato": "B"
    },
    {
      "civico": "210",
      "barrato": "C"
    },
    {
      "civico": "210",
      "barrato": null
    }
  ],
  "VIA FANTATI": [
    {
      "civico": "373",
      "barrato": null
    }
  ],
  "VIA FRAMBANA": [
    {
      "civico": "309",
      "barrato": null
    },
    {
      "civico": "369",
      "barrato": null
    },
    {
      "civico": "373",
      "barrato": "A"
    },
    {
      "civico": "966",
      "barrato": "1"
    },
    {
      "civico": "968",
      "barrato": null
    }
  ],
  "VIA GIACOMO PUCCINI": [
    {
      "civico": "187",
      "barrato": null
    },
    {
      "civico": "189",
      "barrato": null
    },
    {
      "civico": "191",
      "barrato": null
    },
    {
      "civico": "193",
      "barrato": null
    }
  ],
  "VIA GIOVANNI AMENDOLA": [
    {
      "civico": "293",
      "barrato": "B"
    },
    {
      "civico": "293",
      "barrato": "C"
    },
    {
      "civico": "293",
      "barrato": "D"
    },
    {
      "civico": "293",
      "barrato": "E"
    },
    {
      "civico": "293",
      "barrato": "F"
    },
    {
      "civico": "293",
      "barrato": "G"
    },
    {
      "civico": "293",
      "barrato": "H"
    },
    {
      "civico": "293",
      "barrato": "I"
    },
    {
      "civico": "303",
      "barrato": "A"
    },
    {
      "civico": "303",
      "barrato": "B"
    }
  ],
  "VIA GIOVANNI TASSO": [
    {
      "civico": "253",
      "barrato": "A"
    },
    {
      "civico": "253",
      "barrato": "B 1"
    },
    {
      "civico": "253",
      "barrato": "B 10"
    },
    {
      "civico": "253",
      "barrato": "B 11"
    },
    {
      "civico": "253",
      "barrato": "B 12"
    },
    {
      "civico": "253",
      "barrato": "B 14"
    },
    {
      "civico": "253",
      "barrato": "B 15"
    },
    {
      "civico": "253",
      "barrato": "B 16"
    },
    {
      "civico": "253",
      "barrato": "B 17"
    },
    {
      "civico": "253",
      "barrato": "B 18"
    },
    {
      "civico": "253",
      "barrato": "B 19"
    },
    {
      "civico": "253",
      "barrato": "B 2"
    },
    {
      "civico": "253",
      "barrato": "B 20"
    },
    {
      "civico": "253",
      "barrato": "B 3"
    },
    {
      "civico": "253",
      "barrato": "B 4"
    },
    {
      "civico": "253",
      "barrato": "B 5"
    },
    {
      "civico": "253",
      "barrato": "B 6"
    },
    {
      "civico": "253",
      "barrato": "B 7"
    },
    {
      "civico": "253",
      "barrato": "B 8"
    },
    {
      "civico": "253",
      "barrato": "B 9"
    },
    {
      "civico": "434",
      "barrato": null
    },
    {
      "civico": "559",
      "barrato": null
    },
    {
      "civico": "944",
      "barrato": null
    },
    {
      "civico": "976",
      "barrato": null
    },
    {
      "civico": "1154",
      "barrato": null
    },
    {
      "civico": "1210",
      "barrato": null
    },
    {
      "civico": "1580",
      "barrato": null
    },
    {
      "civico": "1596",
      "barrato": null
    },
    {
      "civico": "1612",
      "barrato": null
    },
    {
      "civico": "1624",
      "barrato": null
    },
    {
      "civico": "1634",
      "barrato": null
    }
  ],
  "VIA GIROLAMO LOMBARDI": [
    {
      "civico": "11",
      "barrato": null
    },
    {
      "civico": "13",
      "barrato": null
    },
    {
      "civico": "187",
      "barrato": null
    },
    {
      "civico": "345",
      "barrato": null
    }
  ],
  "VIA GIUSEPPE GARIBALDI": [
    {
      "civico": "359",
      "barrato": null
    }
  ],
  "VIA GUGLIELMO MARCONI": [
    {
      "civico": "287",
      "barrato": null
    },
    {
      "civico": "328",
      "barrato": null
    },
    {
      "civico": "330",
      "barrato": null
    },
    {
      "civico": "332",
      "barrato": null
    },
    {
      "civico": "334",
      "barrato": null
    },
    {
      "civico": "336",
      "barrato": null
    },
    {
      "civico": "338",
      "barrato": null
    },
    {
      "civico": "340",
      "barrato": null
    },
    {
      "civico": "342",
      "barrato": null
    },
    {
      "civico": "344",
      "barrato": null
    },
    {
      "civico": "346",
      "barrato": null
    },
    {
      "civico": "348",
      "barrato": null
    },
    {
      "civico": "350",
      "barrato": null
    },
    {
      "civico": "352",
      "barrato": null
    },
    {
      "civico": "354",
      "barrato": null
    },
    {
      "civico": "356",
      "barrato": null
    },
    {
      "civico": "358",
      "barrato": null
    },
    {
      "civico": "360",
      "barrato": null
    },
    {
      "civico": "362",
      "barrato": null
    },
    {
      "civico": "372",
      "barrato": null
    },
    {
      "civico": "376",
      "barrato": null
    },
    {
      "civico": "378",
      "barrato": null
    },
    {
      "civico": "380",
      "barrato": null
    },
    {
      "civico": "382",
      "barrato": null
    },
    {
      "civico": "384",
      "barrato": null
    },
    {
      "civico": "386",
      "barrato": null
    },
    {
      "civico": "388",
      "barrato": null
    },
    {
      "civico": "390",
      "barrato": null
    },
    {
      "civico": "392",
      "barrato": null
    },
    {
      "civico": "394",
      "barrato": null
    },
    {
      "civico": "396",
      "barrato": null
    },
    {
      "civico": "398",
      "barrato": null
    },
    {
      "civico": "400",
      "barrato": null
    },
    {
      "civico": "404",
      "barrato": null
    },
    {
      "civico": "408",
      "barrato": null
    },
    {
      "civico": "410",
      "barrato": null
    },
    {
      "civico": "412",
      "barrato": null
    },
    {
      "civico": "414",
      "barrato": null
    },
    {
      "civico": "416",
      "barrato": null
    },
    {
      "civico": "418",
      "barrato": null
    },
    {
      "civico": "420",
      "barrato": null
    },
    {
      "civico": "422",
      "barrato": null
    },
    {
      "civico": "424",
      "barrato": null
    },
    {
      "civico": "426",
      "barrato": null
    },
    {
      "civico": "428",
      "barrato": null
    },
    {
      "civico": "430",
      "barrato": null
    },
    {
      "civico": "432",
      "barrato": null
    },
    {
      "civico": "434",
      "barrato": null
    },
    {
      "civico": "436",
      "barrato": null
    },
    {
      "civico": "438",
      "barrato": null
    },
    {
      "civico": "440",
      "barrato": null
    },
    {
      "civico": "442",
      "barrato": null
    },
    {
      "civico": "444",
      "barrato": null
    },
    {
      "civico": "446",
      "barrato": null
    },
    {
      "civico": "448",
      "barrato": null
    },
    {
      "civico": "450",
      "barrato": null
    },
    {
      "civico": "452",
      "barrato": null
    },
    {
      "civico": "454",
      "barrato": null
    },
    {
      "civico": "456",
      "barrato": null
    },
    {
      "civico": "458",
      "barrato": null
    },
    {
      "civico": "460",
      "barrato": null
    },
    {
      "civico": "462",
      "barrato": null
    },
    {
      "civico": "464",
      "barrato": null
    },
    {
      "civico": "466",
      "barrato": null
    },
    {
      "civico": "468",
      "barrato": null
    },
    {
      "civico": "470",
      "barrato": null
    },
    {
      "civico": "472",
      "barrato": null
    },
    {
      "civico": "474",
      "barrato": null
    },
    {
      "civico": "476",
      "barrato": null
    },
    {
      "civico": "478",
      "barrato": null
    },
    {
      "civico": "480",
      "barrato": null
    },
    {
      "civico": "482",
      "barrato": null
    },
    {
      "civico": "484",
      "barrato": null
    },
    {
      "civico": "486",
      "barrato": null
    },
    {
      "civico": "488",
      "barrato": null
    },
    {
      "civico": "490",
      "barrato": null
    },
    {
      "civico": "492",
      "barrato": null
    },
    {
      "civico": "494",
      "barrato": null
    },
    {
      "civico": "496",
      "barrato": null
    },
    {
      "civico": "498",
      "barrato": null
    },
    {
      "civico": "500",
      "barrato": null
    },
    {
      "civico": "502",
      "barrato": null
    },
    {
      "civico": "504",
      "barrato": null
    },
    {
      "civico": "506",
      "barrato": null
    },
    {
      "civico": "508",
      "barrato": null
    },
    {
      "civico": "640",
      "barrato": null
    },
    {
      "civico": "716",
      "barrato": null
    }
  ],
  "VIA I MAGGIO": [
    {
      "civico": "490",
      "barrato": null
    },
    {
      "civico": "492",
      "barrato": null
    },
    {
      "civico": "494",
      "barrato": null
    },
    {
      "civico": "502",
      "barrato": null
    },
    {
      "civico": "504",
      "barrato": null
    },
    {
      "civico": "518",
      "barrato": null
    },
    {
      "civico": "524",
      "barrato": null
    },
    {
      "civico": "528",
      "barrato": null
    },
    {
      "civico": "530",
      "barrato": null
    },
    {
      "civico": "550",
      "barrato": null
    },
    {
      "civico": "552",
      "barrato": null
    },
    {
      "civico": "554",
      "barrato": null
    },
    {
      "civico": "556",
      "barrato": null
    },
    {
      "civico": "586",
      "barrato": null
    },
    {
      "civico": "602",
      "barrato": null
    },
    {
      "civico": "604",
      "barrato": null
    },
    {
      "civico": "608",
      "barrato": null
    },
    {
      "civico": "614",
      "barrato": null
    },
    {
      "civico": "618",
      "barrato": null
    },
    {
      "civico": "626",
      "barrato": null
    },
    {
      "civico": "630",
      "barrato": null
    },
    {
      "civico": "631",
      "barrato": null
    },
    {
      "civico": "633",
      "barrato": null
    },
    {
      "civico": "635",
      "barrato": null
    },
    {
      "civico": "636",
      "barrato": null
    },
    {
      "civico": "637",
      "barrato": null
    },
    {
      "civico": "638",
      "barrato": null
    },
    {
      "civico": "639",
      "barrato": null
    },
    {
      "civico": "640",
      "barrato": null
    },
    {
      "civico": "678",
      "barrato": null
    },
    {
      "civico": "680",
      "barrato": null
    },
    {
      "civico": "682",
      "barrato": null
    },
    {
      "civico": "684",
      "barrato": null
    },
    {
      "civico": "685",
      "barrato": null
    },
    {
      "civico": "686",
      "barrato": null
    },
    {
      "civico": "688",
      "barrato": null
    },
    {
      "civico": "690",
      "barrato": "F"
    },
    {
      "civico": "690",
      "barrato": "G"
    },
    {
      "civico": "690",
      "barrato": "H"
    },
    {
      "civico": "690",
      "barrato": null
    },
    {
      "civico": "696",
      "barrato": null
    },
    {
      "civico": "698",
      "barrato": null
    },
    {
      "civico": "1000",
      "barrato": null
    }
  ],
  "VIA MAGARINO": [
    {
      "civico": "594",
      "barrato": null
    },
    {
      "civico": "598",
      "barrato": null
    },
    {
      "civico": "600",
      "barrato": null
    },
    {
      "civico": "606",
      "barrato": null
    },
    {
      "civico": "608",
      "barrato": null
    },
    {
      "civico": "610",
      "barrato": null
    },
    {
      "civico": "713",
      "barrato": "A"
    },
    {
      "civico": "713",
      "barrato": "B"
    }
  ],
  "VIA NATALE E LUIGI MANEO": [
    {
      "civico": "0",
      "barrato": null
    },
    {
      "civico": "249",
      "barrato": null
    }
  ],
  "VIA PONZILOVO": [
    {
      "civico": "232",
      "barrato": "B"
    }
  ],
  "VIA RACCANO": [
    {
      "civico": "0",
      "barrato": null
    },
    {
      "civico": "10",
      "barrato": null
    },
    {
      "civico": "21",
      "barrato": null
    },
    {
      "civico": "23",
      "barrato": null
    },
    {
      "civico": "26",
      "barrato": "A"
    },
    {
      "civico": "26",
      "barrato": "B"
    },
    {
      "civico": "34",
      "barrato": null
    },
    {
      "civico": "43",
      "barrato": null
    },
    {
      "civico": "59",
      "barrato": null
    },
    {
      "civico": "104",
      "barrato": null
    },
    {
      "civico": "176",
      "barrato": "B"
    },
    {
      "civico": "208",
      "barrato": "C"
    },
    {
      "civico": "208",
      "barrato": "D"
    },
    {
      "civico": "208",
      "barrato": "E"
    },
    {
      "civico": "208",
      "barrato": "F"
    },
    {
      "civico": "218",
      "barrato": "1"
    },
    {
      "civico": "218",
      "barrato": "2"
    },
    {
      "civico": "296",
      "barrato": null
    },
    {
      "civico": "300",
      "barrato": "B"
    },
    {
      "civico": "300",
      "barrato": null
    },
    {
      "civico": "360",
      "barrato": null
    },
    {
      "civico": "552",
      "barrato": null
    },
    {
      "civico": "560",
      "barrato": null
    },
    {
      "civico": "588",
      "barrato": null
    },
    {
      "civico": "620",
      "barrato": null
    },
    {
      "civico": "659",
      "barrato": "AA"
    },
    {
      "civico": "659",
      "barrato": "CC"
    },
    {
      "civico": "659",
      "barrato": "DD"
    },
    {
      "civico": "659",
      "barrato": "E"
    },
    {
      "civico": "659",
      "barrato": "EE"
    },
    {
      "civico": "659",
      "barrato": "FF"
    },
    {
      "civico": "659",
      "barrato": "M"
    },
    {
      "civico": "659",
      "barrato": "P"
    },
    {
      "civico": "659",
      "barrato": "Q"
    },
    {
      "civico": "659",
      "barrato": "T 1"
    },
    {
      "civico": "659",
      "barrato": "T 2"
    },
    {
      "civico": "659",
      "barrato": "V"
    },
    {
      "civico": "659",
      "barrato": "Z"
    },
    {
      "civico": "694",
      "barrato": null
    },
    {
      "civico": "728",
      "barrato": "B"
    },
    {
      "civico": "736",
      "barrato": "A"
    },
    {
      "civico": "736",
      "barrato": "B"
    },
    {
      "civico": "736",
      "barrato": "C"
    },
    {
      "civico": "820",
      "barrato": null
    },
    {
      "civico": "822",
      "barrato": null
    },
    {
      "civico": "876",
      "barrato": null
    },
    {
      "civico": "1606",
      "barrato": null
    },
    {
      "civico": "1973",
      "barrato": null
    },
    {
      "civico": "1991",
      "barrato": null
    },
    {
      "civico": "2011",
      "barrato": null
    },
    {
      "civico": "3733",
      "barrato": null
    },
    {
      "civico": "3853",
      "barrato": null
    },
    {
      "civico": "3917",
      "barrato": null
    },
    {
      "civico": "3981",
      "barrato": "B"
    },
    {
      "civico": "3983",
      "barrato": null
    },
    {
      "civico": "4580",
      "barrato": null
    },
    {
      "civico": "5500",
      "barrato": null
    },
    {
      "civico": "5532",
      "barrato": null
    }
  ],
  "VIA ROMA": [
    {
      "civico": "751",
      "barrato": null
    },
    {
      "civico": "752",
      "barrato": null
    },
    {
      "civico": "753",
      "barrato": null
    },
    {
      "civico": "800",
      "barrato": null
    },
    {
      "civico": "802",
      "barrato": null
    },
    {
      "civico": "804",
      "barrato": null
    },
    {
      "civico": "806",
      "barrato": null
    },
    {
      "civico": "808",
      "barrato": null
    },
    {
      "civico": "810",
      "barrato": null
    },
    {
      "civico": "812",
      "barrato": null
    },
    {
      "civico": "814",
      "barrato": null
    },
    {
      "civico": "827",
      "barrato": null
    },
    {
      "civico": "829",
      "barrato": null
    },
    {
      "civico": "831",
      "barrato": null
    },
    {
      "civico": "840",
      "barrato": null
    },
    {
      "civico": "842",
      "barrato": null
    },
    {
      "civico": "844",
      "barrato": null
    },
    {
      "civico": "846",
      "barrato": null
    },
    {
      "civico": "848",
      "barrato": null
    },
    {
      "civico": "850",
      "barrato": null
    },
    {
      "civico": "891",
      "barrato": null
    },
    {
      "civico": "893",
      "barrato": null
    },
    {
      "civico": "895",
      "barrato": null
    },
    {
      "civico": "897",
      "barrato": null
    },
    {
      "civico": "899",
      "barrato": null
    },
    {
      "civico": "901",
      "barrato": null
    },
    {
      "civico": "912",
      "barrato": null
    },
    {
      "civico": "914",
      "barrato": null
    },
    {
      "civico": "916",
      "barrato": null
    },
    {
      "civico": "920",
      "barrato": null
    },
    {
      "civico": "922",
      "barrato": null
    },
    {
      "civico": "924",
      "barrato": null
    },
    {
      "civico": "926",
      "barrato": null
    },
    {
      "civico": "928",
      "barrato": null
    },
    {
      "civico": "932",
      "barrato": null
    },
    {
      "civico": "934",
      "barrato": null
    },
    {
      "civico": "936",
      "barrato": null
    },
    {
      "civico": "938",
      "barrato": null
    },
    {
      "civico": "940",
      "barrato": null
    },
    {
      "civico": "942",
      "barrato": null
    },
    {
      "civico": "944",
      "barrato": null
    },
    {
      "civico": "946",
      "barrato": null
    },
    {
      "civico": "948",
      "barrato": null
    },
    {
      "civico": "954",
      "barrato": null
    },
    {
      "civico": "956",
      "barrato": null
    },
    {
      "civico": "958",
      "barrato": null
    },
    {
      "civico": "960",
      "barrato": null
    },
    {
      "civico": "1216",
      "barrato": "B"
    },
    {
      "civico": "1216",
      "barrato": "C"
    }
  ],
  "VIA ROMAGNOLA": [
    {
      "civico": "16",
      "barrato": null
    },
    {
      "civico": "377",
      "barrato": null
    },
    {
      "civico": "495",
      "barrato": null
    }
  ],
  "VIA RUBIS ZEMELLA": [
    {
      "civico": "47",
      "barrato": "B"
    }
  ],
  "VIA SAN GAETANO": [
    {
      "civico": "705",
      "barrato": null
    },
    {
      "civico": "709",
      "barrato": null
    },
    {
      "civico": "711",
      "barrato": null
    },
    {
      "civico": "713",
      "barrato": null
    },
    {
      "civico": "715",
      "barrato": null
    },
    {
      "civico": "719",
      "barrato": null
    },
    {
      "civico": "721",
      "barrato": null
    },
    {
      "civico": "723",
      "barrato": null
    },
    {
      "civico": "725",
      "barrato": null
    },
    {
      "civico": "727",
      "barrato": null
    },
    {
      "civico": "729",
      "barrato": null
    },
    {
      "civico": "731",
      "barrato": null
    },
    {
      "civico": "733",
      "barrato": null
    },
    {
      "civico": "735",
      "barrato": null
    },
    {
      "civico": "737",
      "barrato": null
    },
    {
      "civico": "739",
      "barrato": null
    },
    {
      "civico": "741",
      "barrato": null
    },
    {
      "civico": "745",
      "barrato": null
    },
    {
      "civico": "747",
      "barrato": null
    },
    {
      "civico": "749",
      "barrato": null
    },
    {
      "civico": "751",
      "barrato": null
    },
    {
      "civico": "753",
      "barrato": null
    },
    {
      "civico": "757",
      "barrato": null
    },
    {
      "civico": "759",
      "barrato": null
    },
    {
      "civico": "761",
      "barrato": null
    },
    {
      "civico": "763",
      "barrato": null
    },
    {
      "civico": "765",
      "barrato": null
    },
    {
      "civico": "767",
      "barrato": null
    },
    {
      "civico": "769",
      "barrato": null
    },
    {
      "civico": "771",
      "barrato": null
    },
    {
      "civico": "773",
      "barrato": null
    },
    {
      "civico": "775",
      "barrato": null
    },
    {
      "civico": "777",
      "barrato": null
    },
    {
      "civico": "779",
      "barrato": null
    },
    {
      "civico": "781",
      "barrato": null
    },
    {
      "civico": "783",
      "barrato": null
    },
    {
      "civico": "785",
      "barrato": null
    },
    {
      "civico": "787",
      "barrato": null
    },
    {
      "civico": "789",
      "barrato": null
    },
    {
      "civico": "791",
      "barrato": null
    },
    {
      "civico": "793",
      "barrato": null
    },
    {
      "civico": "795",
      "barrato": null
    },
    {
      "civico": "797",
      "barrato": null
    },
    {
      "civico": "799",
      "barrato": null
    },
    {
      "civico": "801",
      "barrato": null
    },
    {
      "civico": "803",
      "barrato": null
    },
    {
      "civico": "805",
      "barrato": null
    },
    {
      "civico": "807",
      "barrato": null
    },
    {
      "civico": "809",
      "barrato": null
    },
    {
      "civico": "811",
      "barrato": null
    },
    {
      "civico": "813",
      "barrato": null
    },
    {
      "civico": "817",
      "barrato": null
    },
    {
      "civico": "819",
      "barrato": null
    },
    {
      "civico": "825",
      "barrato": null
    },
    {
      "civico": "827",
      "barrato": null
    },
    {
      "civico": "829",
      "barrato": null
    },
    {
      "civico": "833",
      "barrato": null
    },
    {
      "civico": "835",
      "barrato": null
    },
    {
      "civico": "839",
      "barrato": null
    },
    {
      "civico": "841",
      "barrato": null
    },
    {
      "civico": "843",
      "barrato": null
    },
    {
      "civico": "845",
      "barrato": null
    },
    {
      "civico": "847",
      "barrato": null
    },
    {
      "civico": "849",
      "barrato": null
    },
    {
      "civico": "851",
      "barrato": null
    },
    {
      "civico": "853",
      "barrato": null
    },
    {
      "civico": "855",
      "barrato": null
    },
    {
      "civico": "957",
      "barrato": null
    },
    {
      "civico": "963",
      "barrato": null
    },
    {
      "civico": "981",
      "barrato": "B"
    },
    {
      "civico": "981",
      "barrato": null
    },
    {
      "civico": "2153",
      "barrato": "A"
    },
    {
      "civico": "2171",
      "barrato": null
    }
  ],
  "VIA TORELLI": [
    {
      "civico": "0",
      "barrato": null
    }
  ],
  "VIA TRENTO": [
    {
      "civico": "191",
      "barrato": null
    }
  ],
  "VIA TRIESTE": [
    {
      "civico": "51",
      "barrato": null
    },
    {
      "civico": "57",
      "barrato": null
    },
    {
      "civico": "583",
      "barrato": null
    },
    {
      "civico": "585",
      "barrato": null
    },
    {
      "civico": "587",
      "barrato": null
    },
    {
      "civico": "589",
      "barrato": null
    },
    {
      "civico": "593",
      "barrato": null
    },
    {
      "civico": "595",
      "barrato": null
    },
    {
      "civico": "597",
      "barrato": null
    },
    {
      "civico": "599",
      "barrato": null
    },
    {
      "civico": "601",
      "barrato": null
    },
    {
      "civico": "603",
      "barrato": null
    },
    {
      "civico": "605",
      "barrato": null
    },
    {
      "civico": "609",
      "barrato": null
    },
    {
      "civico": "611",
      "barrato": null
    },
    {
      "civico": "613",
      "barrato": null
    },
    {
      "civico": "615",
      "barrato": null
    },
    {
      "civico": "617",
      "barrato": null
    },
    {
      "civico": "619",
      "barrato": null
    },
    {
      "civico": "621",
      "barrato": null
    },
    {
      "civico": "623",
      "barrato": null
    },
    {
      "civico": "625",
      "barrato": null
    },
    {
      "civico": "627",
      "barrato": null
    },
    {
      "civico": "629",
      "barrato": null
    },
    {
      "civico": "631",
      "barrato": null
    },
    {
      "civico": "633",
      "barrato": null
    },
    {
      "civico": "635",
      "barrato": null
    },
    {
      "civico": "637",
      "barrato": null
    },
    {
      "civico": "639",
      "barrato": null
    },
    {
      "civico": "641",
      "barrato": null
    },
    {
      "civico": "643",
      "barrato": null
    },
    {
      "civico": "645",
      "barrato": null
    },
    {
      "civico": "647",
      "barrato": null
    },
    {
      "civico": "649",
      "barrato": null
    },
    {
      "civico": "651",
      "barrato": null
    },
    {
      "civico": "655",
      "barrato": null
    },
    {
      "civico": "657",
      "barrato": null
    },
    {
      "civico": "659",
      "barrato": null
    },
    {
      "civico": "661",
      "barrato": null
    },
    {
      "civico": "663",
      "barrato": null
    },
    {
      "civico": "665",
      "barrato": null
    },
    {
      "civico": "667",
      "barrato": null
    },
    {
      "civico": "669",
      "barrato": null
    },
    {
      "civico": "671",
      "barrato": null
    },
    {
      "civico": "673",
      "barrato": null
    },
    {
      "civico": "675",
      "barrato": null
    },
    {
      "civico": "677",
      "barrato": null
    },
    {
      "civico": "679",
      "barrato": null
    },
    {
      "civico": "681",
      "barrato": null
    },
    {
      "civico": "683",
      "barrato": null
    },
    {
      "civico": "685",
      "barrato": null
    },
    {
      "civico": "687",
      "barrato": null
    },
    {
      "civico": "689",
      "barrato": null
    },
    {
      "civico": "691",
      "barrato": null
    },
    {
      "civico": "693",
      "barrato": null
    },
    {
      "civico": "695",
      "barrato": null
    },
    {
      "civico": "697",
      "barrato": null
    },
    {
      "civico": "699",
      "barrato": null
    },
    {
      "civico": "701",
      "barrato": null
    },
    {
      "civico": "703",
      "barrato": null
    },
    {
      "civico": "705",
      "barrato": null
    },
    {
      "civico": "707",
      "barrato": null
    },
    {
      "civico": "709",
      "barrato": null
    },
    {
      "civico": "711",
      "barrato": null
    },
    {
      "civico": "713",
      "barrato": null
    },
    {
      "civico": "715",
      "barrato": null
    },
    {
      "civico": "717",
      "barrato": null
    },
    {
      "civico": "721",
      "barrato": null
    },
    {
      "civico": "723",
      "barrato": null
    },
    {
      "civico": "725",
      "barrato": null
    },
    {
      "civico": "727",
      "barrato": null
    },
    {
      "civico": "729",
      "barrato": null
    },
    {
      "civico": "731",
      "barrato": null
    },
    {
      "civico": "735",
      "barrato": null
    },
    {
      "civico": "739",
      "barrato": null
    },
    {
      "civico": "741",
      "barrato": null
    },
    {
      "civico": "743",
      "barrato": null
    },
    {
      "civico": "745",
      "barrato": null
    },
    {
      "civico": "747",
      "barrato": null
    },
    {
      "civico": "749",
      "barrato": null
    },
    {
      "civico": "751",
      "barrato": null
    },
    {
      "civico": "753",
      "barrato": null
    },
    {
      "civico": "755",
      "barrato": null
    },
    {
      "civico": "757",
      "barrato": null
    },
    {
      "civico": "759",
      "barrato": null
    },
    {
      "civico": "761",
      "barrato": null
    },
    {
      "civico": "763",
      "barrato": null
    },
    {
      "civico": "765",
      "barrato": null
    },
    {
      "civico": "767",
      "barrato": null
    },
    {
      "civico": "769",
      "barrato": null
    },
    {
      "civico": "771",
      "barrato": null
    },
    {
      "civico": "773",
      "barrato": null
    },
    {
      "civico": "775",
      "barrato": null
    },
    {
      "civico": "777",
      "barrato": null
    },
    {
      "civico": "779",
      "barrato": null
    },
    {
      "civico": "783",
      "barrato": null
    },
    {
      "civico": "785",
      "barrato": null
    },
    {
      "civico": "787",
      "barrato": null
    },
    {
      "civico": "789",
      "barrato": null
    },
    {
      "civico": "791",
      "barrato": null
    },
    {
      "civico": "793",
      "barrato": null
    },
    {
      "civico": "795",
      "barrato": null
    },
    {
      "civico": "797",
      "barrato": null
    },
    {
      "civico": "799",
      "barrato": null
    },
    {
      "civico": "801",
      "barrato": null
    },
    {
      "civico": "803",
      "barrato": null
    },
    {
      "civico": "805",
      "barrato": null
    },
    {
      "civico": "809",
      "barrato": null
    },
    {
      "civico": "813",
      "barrato": null
    },
    {
      "civico": "815",
      "barrato": null
    },
    {
      "civico": "817",
      "barrato": null
    },
    {
      "civico": "819",
      "barrato": null
    },
    {
      "civico": "821",
      "barrato": null
    },
    {
      "civico": "827",
      "barrato": null
    },
    {
      "civico": "829",
      "barrato": null
    },
    {
      "civico": "831",
      "barrato": null
    },
    {
      "civico": "833",
      "barrato": null
    },
    {
      "civico": "835",
      "barrato": null
    },
    {
      "civico": "837",
      "barrato": null
    },
    {
      "civico": "839",
      "barrato": null
    },
    {
      "civico": "841",
      "barrato": null
    },
    {
      "civico": "843",
      "barrato": null
    },
    {
      "civico": "845",
      "barrato": null
    },
    {
      "civico": "847",
      "barrato": null
    },
    {
      "civico": "849",
      "barrato": null
    },
    {
      "civico": "851",
      "barrato": null
    },
    {
      "civico": "853",
      "barrato": null
    },
    {
      "civico": "855",
      "barrato": null
    },
    {
      "civico": "857",
      "barrato": null
    },
    {
      "civico": "859",
      "barrato": null
    },
    {
      "civico": "861",
      "barrato": null
    },
    {
      "civico": "863",
      "barrato": null
    },
    {
      "civico": "865",
      "barrato": null
    },
    {
      "civico": "867",
      "barrato": null
    },
    {
      "civico": "869",
      "barrato": null
    },
    {
      "civico": "873",
      "barrato": null
    },
    {
      "civico": "875",
      "barrato": null
    },
    {
      "civico": "877",
      "barrato": null
    },
    {
      "civico": "879",
      "barrato": null
    },
    {
      "civico": "881",
      "barrato": null
    },
    {
      "civico": "883",
      "barrato": null
    },
    {
      "civico": "885",
      "barrato": null
    },
    {
      "civico": "887",
      "barrato": null
    },
    {
      "civico": "889",
      "barrato": null
    },
    {
      "civico": "891",
      "barrato": null
    },
    {
      "civico": "893",
      "barrato": null
    },
    {
      "civico": "895",
      "barrato": null
    },
    {
      "civico": "897",
      "barrato": null
    },
    {
      "civico": "899",
      "barrato": null
    },
    {
      "civico": "901",
      "barrato": null
    },
    {
      "civico": "903",
      "barrato": null
    },
    {
      "civico": "905",
      "barrato": null
    },
    {
      "civico": "907",
      "barrato": null
    },
    {
      "civico": "911",
      "barrato": null
    },
    {
      "civico": "913",
      "barrato": null
    },
    {
      "civico": "915",
      "barrato": null
    },
    {
      "civico": "917",
      "barrato": null
    },
    {
      "civico": "919",
      "barrato": null
    },
    {
      "civico": "921",
      "barrato": null
    },
    {
      "civico": "923",
      "barrato": null
    },
    {
      "civico": "925",
      "barrato": null
    },
    {
      "civico": "927",
      "barrato": null
    },
    {
      "civico": "929",
      "barrato": null
    },
    {
      "civico": "931",
      "barrato": null
    },
    {
      "civico": "933",
      "barrato": null
    },
    {
      "civico": "935",
      "barrato": null
    },
    {
      "civico": "937",
      "barrato": null
    },
    {
      "civico": "939",
      "barrato": null
    },
    {
      "civico": "941",
      "barrato": null
    },
    {
      "civico": "943",
      "barrato": null
    },
    {
      "civico": "945",
      "barrato": null
    },
    {
      "civico": "947",
      "barrato": null
    },
    {
      "civico": "949",
      "barrato": null
    },
    {
      "civico": "951",
      "barrato": null
    },
    {
      "civico": "953",
      "barrato": null
    },
    {
      "civico": "955",
      "barrato": null
    },
    {
      "civico": "957",
      "barrato": null
    },
    {
      "civico": "959",
      "barrato": null
    },
    {
      "civico": "961",
      "barrato": null
    },
    {
      "civico": "963",
      "barrato": null
    },
    {
      "civico": "965",
      "barrato": null
    },
    {
      "civico": "967",
      "barrato": null
    },
    {
      "civico": "969",
      "barrato": null
    },
    {
      "civico": "971",
      "barrato": null
    },
    {
      "civico": "973",
      "barrato": null
    },
    {
      "civico": "975",
      "barrato": null
    },
    {
      "civico": "977",
      "barrato": null
    },
    {
      "civico": "979",
      "barrato": null
    },
    {
      "civico": "981",
      "barrato": null
    },
    {
      "civico": "983",
      "barrato": null
    },
    {
      "civico": "985",
      "barrato": null
    },
    {
      "civico": "987",
      "barrato": null
    },
    {
      "civico": "989",
      "barrato": null
    },
    {
      "civico": "991",
      "barrato": null
    },
    {
      "civico": "993",
      "barrato": null
    },
    {
      "civico": "995",
      "barrato": null
    },
    {
      "civico": "999",
      "barrato": null
    },
    {
      "civico": "1001",
      "barrato": null
    },
    {
      "civico": "1003",
      "barrato": null
    },
    {
      "civico": "1005",
      "barrato": null
    },
    {
      "civico": "1007",
      "barrato": null
    },
    {
      "civico": "1011",
      "barrato": null
    },
    {
      "civico": "1013",
      "barrato": null
    },
    {
      "civico": "1015",
      "barrato": null
    },
    {
      "civico": "1017",
      "barrato": null
    },
    {
      "civico": "1019",
      "barrato": null
    },
    {
      "civico": "1021",
      "barrato": null
    },
    {
      "civico": "1023",
      "barrato": null
    },
    {
      "civico": "1025",
      "barrato": null
    },
    {
      "civico": "1029",
      "barrato": null
    },
    {
      "civico": "1031",
      "barrato": null
    },
    {
      "civico": "1033",
      "barrato": null
    },
    {
      "civico": "1035",
      "barrato": null
    },
    {
      "civico": "1037",
      "barrato": null
    },
    {
      "civico": "1039",
      "barrato": null
    },
    {
      "civico": "1041",
      "barrato": null
    },
    {
      "civico": "1043",
      "barrato": null
    },
    {
      "civico": "1047",
      "barrato": null
    },
    {
      "civico": "1049",
      "barrato": null
    },
    {
      "civico": "1051",
      "barrato": null
    },
    {
      "civico": "1053",
      "barrato": null
    },
    {
      "civico": "1055",
      "barrato": null
    },
    {
      "civico": "1057",
      "barrato": null
    },
    {
      "civico": "1059",
      "barrato": null
    },
    {
      "civico": "1061",
      "barrato": null
    },
    {
      "civico": "1063",
      "barrato": null
    },
    {
      "civico": "1065",
      "barrato": null
    },
    {
      "civico": "1067",
      "barrato": null
    },
    {
      "civico": "1069",
      "barrato": null
    },
    {
      "civico": "1071",
      "barrato": null
    },
    {
      "civico": "1073",
      "barrato": null
    },
    {
      "civico": "1075",
      "barrato": null
    },
    {
      "civico": "1077",
      "barrato": null
    },
    {
      "civico": "1081",
      "barrato": null
    }
  ],
  "VIA UGATTI": [
    {
      "civico": "63",
      "barrato": "A"
    },
    {
      "civico": "63",
      "barrato": "A 2"
    },
    {
      "civico": "63",
      "barrato": "B"
    },
    {
      "civico": "63",
      "barrato": "B 1"
    },
    {
      "civico": "63",
      "barrato": "B 3"
    },
    {
      "civico": "80",
      "barrato": "16"
    },
    {
      "civico": "80",
      "barrato": "20"
    },
    {
      "civico": "80",
      "barrato": "30"
    },
    {
      "civico": "80",
      "barrato": "38"
    },
    {
      "civico": "210",
      "barrato": "26"
    },
    {
      "civico": "210",
      "barrato": "30"
    }
  ]
}