{
  "CONTRADA CANCELLI": [
    {
      "civico": "0",
      "barrato": "SNC"
    },
    {
      "civico": "3",
      "barrato": null
    },
    {
      "civico": "7",
      "barrato": null
    },
    {
      "civico": "9",
      "barrato": null
    },
    {
      "civico": "11",
      "barrato": null
    },
    {
      "civico": "16",
      "barrato": null
    },
    {
      "civico": "18",
      "barrato": null
    },
    {
      "civico": "19",
      "barrato": null
    },
    {
      "civico": "27",
      "barrato": null
    }
  ],
  "CONTRADA CASA BIANCA": [
    {
      "civico": "7",
      "barrato": null
    },
    {
      "civico": "11",
      "barrato": null
    },
    {
      "civico": "22",
      "barrato": null
    },
    {
      "civico": "26",
      "barrato": null
    }
  ],
  "CONTRADA COLLE DELLA MORTE": [
    {
      "civico": "2",
      "barrato": "A"
    },
    {
      "civico": "12",
      "barrato": "B"
    }
  ],
  "CONTRADA CONVENTO": [
    {
      "civico": "1",
      "barrato": null
    },
    {
      "civico": "3",
      "barrato": null
    },
    {
      "civico": "5",
      "barrato": null
    },
    {
      "civico": "6",
      "barrato": null
    },
    {
      "civico": "8",
      "barrato": null
    },
    {
      "civico": "50",
      "barrato": null
    }
  ],
  "CONTRADA FONTE FERRAGINE": [
    {
      "civico": "0",
      "barrato": null
    }
  ],
  "CONTRADA PIAGGE": [
    {
      "civico": "2",
      "barrato": null
    },
    {
      "civico": "6",
      "barrato": null
    },
    {
      "civico": "7",
      "barrato": null
    },
    {
      "civico": "9",
      "barrato": null
    },
    {
      "civico": "12",
      "barrato": null
    },
    {
      "civico": "13",
      "barrato": null
    },
    {
      "civico": "14",
      "barrato": null
    },
    {
      "civico": "15",
      "barrato": null
    },
    {
      "civico": "16",
      "barrato": null
    }
  ],
  "CONTRADA PIANCERRETO": [
    {
      "civico": "11",
      "barrato": null
    }
  ],
  "CONTRADA PIZZANNOCCA": [
    {
      "civico": "0",
      "barrato": null
    },
    {
      "civico": "11",
      "barrato": null
    },
    {
      "civico": "18",
      "barrato": null
    },
    {
      "civico": "19",
      "barrato": null
    },
    {
      "civico": "20",
      "barrato": null
    },
    {
      "civico": "21",
      "barrato": null
    },
    {
      "civico": "23",
      "barrato": null
    }
  ],
  "CONTRADA PLAVIGNANO": [
    {
      "civico": "20",
      "barrato": null
    }
  ],
  "CONTRADA QUARTIGLI": [
    {
      "civico": "0",
      "barrato": null
    },
    {
      "civico": "1",
      "barrato": "A"
    },
    {
      "civico": "8",
      "barrato": null
    },
    {
      "civico": "9",
      "barrato": null
    }
  ],
  "CONTRADA RUOTE FINO": [
    {
      "civico": "6",
      "barrato": null
    },
    {
      "civico": "7",
      "barrato": null
    },
    {
      "civico": "9",
      "barrato": null
    }
  ],
  "CONTRADA SAN GIOVANNI": [
    {
      "civico": "0",
      "barrato": "SNC"
    }
  ],
  "CONTRADA SAN POLO": [
    {
      "civico": "1",
      "barrato": "1"
    },
    {
      "civico": "1",
      "barrato": "2"
    }
  ],
  "CONTRADA SANTA CROCE": [
    {
      "civico": "4",
      "barrato": null
    },
    {
      "civico": "6",
      "barrato": "A"
    },
    {
      "civico": "6",
      "barrato": null
    },
    {
      "civico": "7",
      "barrato": null
    },
    {
      "civico": "8",
      "barrato": null
    }
  ],
  "CONTRADA SCOLANNE": [
    {
      "civico": "1",
      "barrato": null
    },
    {
      "civico": "3",
      "barrato": null
    }
  ],
  "CONTRADA TORRETTE": [
    {
      "civico": "1",
      "barrato": null
    },
    {
      "civico": "2",
      "barrato": null
    },
    {
      "civico": "3",
      "barrato": null
    },
    {
      "civico": "4",
      "barrato": null
    }
  ],
  "CONTRADA VICENNE": [
    {
      "civico": "8",
      "barrato": null
    },
    {
      "civico": "10",
      "barrato": null
    },
    {
      "civico": "11",
      "barrato": null
    },
    {
      "civico": "12",
      "barrato": null
    },
    {
      "civico": "13",
      "barrato": null
    },
    {
      "civico": "17",
      "barrato": null
    },
    {
      "civico": "35",
      "barrato": null
    },
    {
      "civico": "37",
      "barrato": null
    },
    {
      "civico": "44",
      "barrato": null
    }
  ],
  "PIAZZA GUGLIELMO MARCONI": [
    {
      "civico": "0",
      "barrato": null
    }
  ],
  "PIAZZA UMBERTO I": [
    {
      "civico": "0",
      "barrato": null
    }
  ],
  "STRADA STATALE 81": [
    {
      "civico": "1",
      "barrato": null
    }
  ],
  "VIA COLLINA": [
    {
      "civico": "0",
      "barrato": null
    }
  ],
  "VIA DANTE ALIGHIERI": [
    {
      "civico": "4",
      "barrato": null
    }
  ],
  "VIA DEL SOLE": [
    {
      "civico": "2",
      "barrato": null
    },
    {
      "civico": "4",
      "barrato": null
    }
  ],
  "VIA DELLA FONTANA VECCHIA": [
    {
      "civico": "0",
      "barrato": null
    }
  ],
  "VIA DUCA DEGLI ABRUZZI": [
    {
      "civico": "0",
      "barrato": null
    }
  ],
  "VIA GRAN SASSO": [
    {
      "civico": "3",
      "barrato": null
    },
    {
      "civico": "13",
      "barrato": null
    },
    {
      "civico": "14",
      "barrato": null
    },
    {
      "civico": "15",
      "barrato": null
    }
  ],
  "VIA PIANCERRETO": [
    {
      "civico": "12",
      "barrato": null
    }
  ],
  "VIA SANTA VITTORIA": [
    {
      "civico": "0",
      "barrato": null
    }
  ],
  "VIA TERAMO": [
    {
      "civico": "5",
      "barrato": null
    }
  ],
  "VIALE ABRUZZO": [
    {
      "civico": "0",
      "barrato": null
    },
    {
      "civico": "1",
      "barrato": null
    },
    {
      "civico": "29",
      "barrato": null
    },
    {
      "civico": "31",
      "barrato": "BIS"
    },
    {
      "civico": "31",
      "barrato": null
    }
  ],
  "VIALE DEI PINI": [
    {
      "civico": "0",
      "barrato": null
    }
  ],
  "VIALE DEL CIPPO ROMANO": [
    {
      "civico": "16",
      "barrato": null
    },
    {
      "civico": "18",
      "barrato": null
    }
  ],
  "VIALE FINO": [
    {
      "civico": "1",
      "barrato": null
    },
    {
      "civico": "2",
      "barrato": null
    },
    {
      "civico": "3",
      "barrato": "A"
    },
    {
      "civico": "3",
      "barrato": "BIS"
    },
    {
      "civico": "5",
      "barrato": null
    },
    {
      "civico": "8",
      "barrato": null
    }
  ],
  "VIALE MONTE OLIVETO": [
    {
      "civico": "6",
      "barrato": null
    }
  ]
}